Workbook
Name CommBond: Portfolio!$G$12
Name CommETF: Portfolio!$G$11
Name NoteLimit: Portfolio!$G$15
Name PlanHoldings: Portfolio!$B$20:$C$30
Name StartCash: Portfolio!$G$10

Sheet Portfolio
B1: Team Caplet WInS portfolio
B2: Laura's plan on 2 Jan 2028, after both deposits, scaled to WInS's $300,000 starting cash. Provisional until the team votes on 1 Oct 2026.
B3: Blue = input you can change. Green = pulled from another tab. Black = formula. Units held and cash update from the Trade Log tab.
B5: Key numbers
B6: Portfolio value | C6: Cash | D6: Return since start | E6: Trades used | F6: Trades left | G6: Commissions paid | H6: Trades outside the plan
B7: =C7+SUM(J20:J30) -> 300000 | C7: =G10+SUM('Trade Log'!K2:K1000) -> 300000 | D7: =IF(G10=0,0,B7/G10-1) -> 0 | E7: =COUNTA('Trade Log'!C2:C1000) -> 0 | F7: =G13-E7 -> 200 | G7: =SUM('Trade Log'!I2:I1000) -> 0 | H7: =SUMPRODUCT(('Trade Log'!C2:C1000<>"")*(COUNTIF($B$20:$B$30,'Trade Log'!C2:C1000)=0)) -> 0
B9: Plan split | F9: WInS rules
B10: Payment ladder | C10: 0.659 | D10: Share of Laura's money on 2 Jan 2028 | F10: Starting cash ($) | G10: 300000 | H10: Session Rules
B11: Facility floor | C11: 0.243 | D11: 25.3% in the plan; 1 point kept as WInS cash | F11: Commission, stock or ETF ($) | G11: 25 | H11: Session Rules
B12: Stock fund | C12: 0.087 | D12: Share of Laura's money on 2 Jan 2028 | F12: Commission, Treasury bond ($) | G12: 10 | H12: Session Rules
B13: Cash | C13: =1-SUM(C10:C12) -> 0.011 | D13: For commissions and rounding | F13: Trade cap | G13: 200 | H13: Session Rules
F14: Position limit per security | G14: 2 | H14: 200% stocks/ETFs; 100% bonds
F15: Trade note limit (characters) | G15: 300 | H15: WInS note box
F16: WInS username | G16: Caplet-10465936 | H16: Must match roster and IPS
B18: Holdings
B19: Holding | C19: Job | D19: Type | E19: Target weight | F19: Target ($) | G19: Price | H19: Target units | I19: Units held | J19: Market value ($) | K19: Actual weight | L19: Drift vs target | M19: Status
B20: IBTM | C20: Jan 2033 payment + facility floor | D20: ETF | E20: =$C$10*'Book L'!$J$14/'Book L'!$J$24+$C$11 -> 0.32529464 | F20: =E20*$G$10 -> 97588.393 | G20: 21.75 | H20: =IF(G20=0,0,IF(D20="Treasury bond",FLOOR(F20/G20*100,1000),FLOOR(F20/G20,1))) -> 4486 | I20: =SUMIFS('Trade Log'!$F:$F,'Trade Log'!$C:$C,$B20,'Trade Log'!$E:$E,"Buy")-SUMIFS('Trade Log'!$F:$F,'Trade Log'!$C:$C,$B20,'Trade Log'!$E:$E,"Sell") -> 0 | J20: =IF(D20="Treasury bond",I20*G20/100,I20*G20) -> 0 | K20: =IF($B$7=0,0,J20/$B$7) -> 0 | L20: =K20-E20 -> -0.32529464 | M20: Listed in WInS; vote pending
B21: IBTO | C21: Jan 2034 payment | D21: ETF | E21: =$C$10*'Book L'!$J$15/'Book L'!$J$24 -> 0.078000254 | F21: =E21*$G$10 -> 23400.076 | G21: 23 | H21: =IF(G21=0,0,IF(D21="Treasury bond",FLOOR(F21/G21*100,1000),FLOOR(F21/G21,1))) -> 1017 | I21: =SUMIFS('Trade Log'!$F:$F,'Trade Log'!$C:$C,$B21,'Trade Log'!$E:$E,"Buy")-SUMIFS('Trade Log'!$F:$F,'Trade Log'!$C:$C,$B21,'Trade Log'!$E:$E,"Sell") -> 0 | J21: =IF(D21="Treasury bond",I21*G21/100,I21*G21) -> 0 | K21: =IF($B$7=0,0,J21/$B$7) -> 0 | L21: =K21-E21 -> -0.078000254 | M21: Listed in WInS; vote pending
B22: IBTP | C22: Jan 2035 payment | D22: ETF | E22: =$C$10*'Book L'!$J$16/'Book L'!$J$24 -> 0.073929074 | F22: =E22*$G$10 -> 22178.722 | G22: 24.09 | H22: =IF(G22=0,0,IF(D22="Treasury bond",FLOOR(F22/G22*100,1000),FLOOR(F22/G22,1))) -> 920 | I22: =SUMIFS('Trade Log'!$F:$F,'Trade Log'!$C:$C,$B22,'Trade Log'!$E:$E,"Buy")-SUMIFS('Trade Log'!$F:$F,'Trade Log'!$C:$C,$B22,'Trade Log'!$E:$E,"Sell") -> 0 | J22: =IF(D22="Treasury bond",I22*G22/100,I22*G22) -> 0 | K22: =IF($B$7=0,0,J22/$B$7) -> 0 | L22: =K22-E22 -> -0.073929074 | M22: Listed in WInS; vote pending
B23: IBTQ | C23: Jan 2036 payment | D23: ETF | E23: =$C$10*'Book L'!$J$17/'Book L'!$J$24 -> 0.070001079 | F23: =E23*$G$10 -> 21000.324 | G23: 23.68 | H23: =IF(G23=0,0,IF(D23="Treasury bond",FLOOR(F23/G23*100,1000),FLOOR(F23/G23,1))) -> 886 | I23: =SUMIFS('Trade Log'!$F:$F,'Trade Log'!$C:$C,$B23,'Trade Log'!$E:$E,"Buy")-SUMIFS('Trade Log'!$F:$F,'Trade Log'!$C:$C,$B23,'Trade Log'!$E:$E,"Sell") -> 0 | J23: =IF(D23="Treasury bond",I23*G23/100,I23*G23) -> 0 | K23: =IF($B$7=0,0,J23/$B$7) -> 0 | L23: =K23-E23 -> -0.070001079 | M23: Listed in WInS; vote pending
B24: IBTR | C24: Jan 2037 payment | D24: ETF | E24: =$C$10*'Book L'!$J$18/'Book L'!$J$24 -> 0.066176785 | F24: =E24*$G$10 -> 19853.035 | G24: 23.46 | H24: =IF(G24=0,0,IF(D24="Treasury bond",FLOOR(F24/G24*100,1000),FLOOR(F24/G24,1))) -> 846 | I24: =SUMIFS('Trade Log'!$F:$F,'Trade Log'!$C:$C,$B24,'Trade Log'!$E:$E,"Buy")-SUMIFS('Trade Log'!$F:$F,'Trade Log'!$C:$C,$B24,'Trade Log'!$E:$E,"Sell") -> 0 | J24: =IF(D24="Treasury bond",I24*G24/100,I24*G24) -> 0 | K24: =IF($B$7=0,0,J24/$B$7) -> 0 | L24: =K24-E24 -> -0.066176785 | M24: Listed in WInS; vote pending
B25: T 4.750% 15-Feb-2037 | C25: Jan 2038 payment | D25: Treasury bond | E25: =$C$10*'Book L'!$J$19/'Book L'!$J$24 -> 0.06609818 | F25: =E25*$G$10 -> 19829.454 | G25: ='Book L'!G19+'Book L'!H19 -> 97.712 | H25: =IF(G25=0,0,IF(D25="Treasury bond",FLOOR(F25/G25*100,1000),FLOOR(F25/G25,1))) -> 20000 | I25: =SUMIFS('Trade Log'!$F:$F,'Trade Log'!$C:$C,$B25,'Trade Log'!$E:$E,"Buy")-SUMIFS('Trade Log'!$F:$F,'Trade Log'!$C:$C,$B25,'Trade Log'!$E:$E,"Sell") -> 0 | J25: =IF(D25="Treasury bond",I25*G25/100,I25*G25) -> 0 | K25: =IF($B$7=0,0,J25/$B$7) -> 0 | L25: =K25-E25 -> -0.06609818 | M25: Price checked (-8bp); vote pending
B26: T 4.500% 15-May-2038 | C26: Jan 2039 payment | D26: Treasury bond | E26: =$C$10*'Book L'!$J$20/'Book L'!$J$24 -> 0.061997913 | F26: =E26*$G$10 -> 18599.374 | G26: ='Book L'!G20+'Book L'!H20 -> 94.811 | H26: =IF(G26=0,0,IF(D26="Treasury bond",FLOOR(F26/G26*100,1000),FLOOR(F26/G26,1))) -> 19000 | I26: =SUMIFS('Trade Log'!$F:$F,'Trade Log'!$C:$C,$B26,'Trade Log'!$E:$E,"Buy")-SUMIFS('Trade Log'!$F:$F,'Trade Log'!$C:$C,$B26,'Trade Log'!$E:$E,"Sell") -> 0 | J26: =IF(D26="Treasury bond",I26*G26/100,I26*G26) -> 0 | K26: =IF($B$7=0,0,J26/$B$7) -> 0 | L26: =K26-E26 -> -0.061997913 | M26: Price checked (+6bp); vote pending
B27: T 4.375% 15-Nov-2039 | C27: Jan 2040 payment | D27: Treasury bond | E27: =$C$10*'Book L'!$J$21/'Book L'!$J$24 -> 0.056600761 | F27: =E27*$G$10 -> 16980.228 | G27: ='Book L'!G21+'Book L'!H21 -> 92.969 | H27: =IF(G27=0,0,IF(D27="Treasury bond",FLOOR(F27/G27*100,1000),FLOOR(F27/G27,1))) -> 18000 | I27: =SUMIFS('Trade Log'!$F:$F,'Trade Log'!$C:$C,$B27,'Trade Log'!$E:$E,"Buy")-SUMIFS('Trade Log'!$F:$F,'Trade Log'!$C:$C,$B27,'Trade Log'!$E:$E,"Sell") -> 0 | J27: =IF(D27="Treasury bond",I27*G27/100,I27*G27) -> 0 | K27: =IF($B$7=0,0,J27/$B$7) -> 0 | L27: =K27-E27 -> -0.056600761 | M27: Price checked (+13bp); vote pending
B28: T 4.250% 15-Nov-2040 | C28: Jan 2041 payment | D28: Treasury bond | E28: =$C$10*'Book L'!$J$22/'Book L'!$J$24 -> 0.053208205 | F28: =E28*$G$10 -> 15962.462 | G28: ='Book L'!G22+'Book L'!H22 -> 90.758 | H28: =IF(G28=0,0,IF(D28="Treasury bond",FLOOR(F28/G28*100,1000),FLOOR(F28/G28,1))) -> 17000 | I28: =SUMIFS('Trade Log'!$F:$F,'Trade Log'!$C:$C,$B28,'Trade Log'!$E:$E,"Buy")-SUMIFS('Trade Log'!$F:$F,'Trade Log'!$C:$C,$B28,'Trade Log'!$E:$E,"Sell") -> 0 | J28: =IF(D28="Treasury bond",I28*G28/100,I28*G28) -> 0 | K28: =IF($B$7=0,0,J28/$B$7) -> 0 | L28: =K28-E28 -> -0.053208205 | M28: Price checked (+14bp); vote pending
B29: T 3.125% 15-Nov-2041 | C29: Jan 2042 payment | D29: Treasury bond | E29: =$C$10*'Book L'!$J$23/'Book L'!$J$24 -> 0.050693107 | F29: =E29*$G$10 -> 15207.932 | G29: ='Book L'!G23+'Book L'!H23 -> 77.523 | H29: =IF(G29=0,0,IF(D29="Treasury bond",FLOOR(F29/G29*100,1000),FLOOR(F29/G29,1))) -> 19000 | I29: =SUMIFS('Trade Log'!$F:$F,'Trade Log'!$C:$C,$B29,'Trade Log'!$E:$E,"Buy")-SUMIFS('Trade Log'!$F:$F,'Trade Log'!$C:$C,$B29,'Trade Log'!$E:$E,"Sell") -> 0 | J29: =IF(D29="Treasury bond",I29*G29/100,I29*G29) -> 0 | K29: =IF($B$7=0,0,J29/$B$7) -> 0 | L29: =K29-E29 -> -0.050693107 | M29: Price checked (+15bp); vote pending
B30: VT | C30: Growth: world stock fund | D30: ETF | E30: =$C$12 -> 0.087 | F30: =E30*$G$10 -> 26100 | G30: 158.45 | H30: =IF(G30=0,0,IF(D30="Treasury bond",FLOOR(F30/G30*100,1000),FLOOR(F30/G30,1))) -> 164 | I30: =SUMIFS('Trade Log'!$F:$F,'Trade Log'!$C:$C,$B30,'Trade Log'!$E:$E,"Buy")-SUMIFS('Trade Log'!$F:$F,'Trade Log'!$C:$C,$B30,'Trade Log'!$E:$E,"Sell") -> 0 | J30: =IF(D30="Treasury bond",I30*G30/100,I30*G30) -> 0 | K30: =IF($B$7=0,0,J30/$B$7) -> 0 | L30: =K30-E30 -> -0.087 | M30: Listed in WInS; vote pending
B31: Cash | C31: Commissions and rounding | D31: Cash | E31: =$C$13 -> 0.011 | F31: =E31*$G$10 -> 3300 | J31: =$C$7 -> 300000 | K31: =IF($B$7=0,0,J31/$B$7) -> 1 | L31: =K31-E31 -> 0.989 | M31: Keep at least $1,000
B32: Total | E32: =SUM(E20:E31) -> 1 | F32: =SUM(F20:F31) -> 300000 | J32: =SUM(J20:J31) -> 300000 | K32: =SUM(K20:K31) -> 1

Sheet Book L
A1: Book L: Laura's first deposit as a literal ladder
A2: Alternative WInS book for the D3 vote. WInS's $300,000 = Laura's 1 Jan 2027 deposit, dollar for dollar: one holding for each $50,000 payment. The stock fund is absent because it is bought with the 2028 deposit, which WInS never receives. Provisional; nothing traded.
A3: Blue text = input. Green = link to the Portfolio tab. Black = formula. Each holding is sized to be worth $50,000 on its payment date with interest reinvested.
A5: Inputs | D5: Summary
A6: Starting cash ($) | B6: =StartCash -> 300000 | D6: Ladder cost ($) | E6: =SUM(J14:J23) -> 292257.1
A7: Commission per ETF trade ($) | B7: =CommETF -> 25 | D7: Commissions ($) | E7: =COUNTIF(C14:C23,"ETF")*B7+COUNTIF(C14:C23,"Treasury bond")*B8 -> 175
A8: Commission per bond trade ($) | B8: =CommBond -> 10 | D8: Cash left ($) | E8: =B6-E6-E7 -> 7567.9
A9: Payment per year ($) | B9: 50000 | D9: Cash left (% of starting cash) | E9: =IF(B6=0,0,E8/B6) -> 0.025226333
D10: Trades needed | E10: =COUNTA(B14:B23) -> 10
A12: Holdings
A13: Pays Laura on 1 Jan | B13: Holding | C13: Type | D13: Ends or matures | E13: Discount factor (28 Sep curve) | F13: Target value today ($) | G13: Price (ETF per share; bond clean per $100) | H13: Accrued interest per $100 face | I13: Size (shares, or face $ for bonds) | J13: Cost ($) | K13: Weight | L13: Note
A14: 2033 | B14: IBTM | C14: ETF | D14: 15 Dec 2032 | E14: 0.729825 | F14: =$B$9*E14 -> 36491.25 | G14: 21.75 | I14: =IF(C14="Treasury bond",ROUNDUP(F14/((G14+H14)/100),-3),ROUNDUP(F14/G14,0)) -> 1678 | J14: =IF(C14="Treasury bond",I14*(G14+H14)/100,I14*G14) -> 36496.5 | K14: =IF($B$6=0,0,J14/$B$6) -> 0.121655 | L14: iShares iBonds Dec 2032 Term Treasury ETF. Also the building-minimum fund in the current plan
A15: 2034 | B15: IBTO | C15: ETF | D15: 15 Dec 2033 | E15: 0.691509 | F15: =$B$9*E15 -> 34575.45 | G15: 23 | I15: =IF(C15="Treasury bond",ROUNDUP(F15/((G15+H15)/100),-3),ROUNDUP(F15/G15,0)) -> 1504 | J15: =IF(C15="Treasury bond",I15*(G15+H15)/100,I15*G15) -> 34592 | K15: =IF($B$6=0,0,J15/$B$6) -> 0.11530667 | L15: iBonds Dec 2033. Not IBTN, which is an unrelated company in WInS
A16: 2035 | B16: IBTP | C16: ETF | D16: 15 Dec 2034 | E16: 0.655288 | F16: =$B$9*E16 -> 32764.4 | G16: 24.09 | I16: =IF(C16="Treasury bond",ROUNDUP(F16/((G16+H16)/100),-3),ROUNDUP(F16/G16,0)) -> 1361 | J16: =IF(C16="Treasury bond",I16*(G16+H16)/100,I16*G16) -> 32786.49 | K16: =IF($B$6=0,0,J16/$B$6) -> 0.1092883 | L16: iBonds Dec 2034
A17: 2036 | B17: IBTQ | C17: ETF | D17: 15 Dec 2035 | E17: 0.620501 | F17: =$B$9*E17 -> 31025.05 | G17: 23.68 | I17: =IF(C17="Treasury bond",ROUNDUP(F17/((G17+H17)/100),-3),ROUNDUP(F17/G17,0)) -> 1311 | J17: =IF(C17="Treasury bond",I17*(G17+H17)/100,I17*G17) -> 31044.48 | K17: =IF($B$6=0,0,J17/$B$6) -> 0.1034816 | L17: iBonds Dec 2035
A18: 2037 | B18: IBTR | C18: ETF | D18: 15 Dec 2036 | E18: 0.586914 | F18: =$B$9*E18 -> 29345.7 | G18: 23.46 | I18: =IF(C18="Treasury bond",ROUNDUP(F18/((G18+H18)/100),-3),ROUNDUP(F18/G18,0)) -> 1251 | J18: =IF(C18="Treasury bond",I18*(G18+H18)/100,I18*G18) -> 29348.46 | K18: =IF($B$6=0,0,J18/$B$6) -> 0.0978282 | L18: iBonds Dec 2036
A19: 2038 | B19: T 4.750% 15-Feb-2037 | C19: Treasury bond | D19: 15 Feb 2037 | E19: 0.581302 | F19: =$B$9*E19 -> 29065.1 | G19: 97.152 | H19: 0.56 | I19: =IF(C19="Treasury bond",ROUNDUP(F19/((G19+H19)/100),-3),ROUNDUP(F19/G19,0)) -> 30000 | J19: =IF(C19="Treasury bond",I19*(G19+H19)/100,I19*G19) -> 29313.6 | K19: =IF($B$6=0,0,J19/$B$6) -> 0.097712 | L19: WInS price checked against the curve (-8bp). Coupons reinvested
A20: 2039 | B20: T 4.500% 15-May-2038 | C20: Treasury bond | D20: 15 May 2038 | E20: 0.541306 | F20: =$B$9*E20 -> 27065.3 | G20: 94.281 | H20: 0.53 | I20: =IF(C20="Treasury bond",ROUNDUP(F20/((G20+H20)/100),-3),ROUNDUP(F20/G20,0)) -> 29000 | J20: =IF(C20="Treasury bond",I20*(G20+H20)/100,I20*G20) -> 27495.19 | K20: =IF($B$6=0,0,J20/$B$6) -> 0.091650633 | L20: Used instead of the 4.375% Feb 2038, whose WInS price is stale (about 85bp off)
A21: 2040 | B21: T 4.375% 15-Nov-2039 | C21: Treasury bond | D21: 15 Nov 2039 | E21: 0.49554 | F21: =$B$9*E21 -> 24777 | G21: 91.363 | H21: 1.606 | I21: =IF(C21="Treasury bond",ROUNDUP(F21/((G21+H21)/100),-3),ROUNDUP(F21/G21,0)) -> 27000 | J21: =IF(C21="Treasury bond",I21*(G21+H21)/100,I21*G21) -> 25101.63 | K21: =IF($B$6=0,0,J21/$B$6) -> 0.0836721 | L21: WInS price checked against the curve (+13bp)
A22: 2041 | B22: T 4.250% 15-Nov-2040 | C22: Treasury bond | D22: 15 Nov 2040 | E22: 0.466558 | F22: =$B$9*E22 -> 23327.9 | G22: 89.186 | H22: 1.572 | I22: =IF(C22="Treasury bond",ROUNDUP(F22/((G22+H22)/100),-3),ROUNDUP(F22/G22,0)) -> 26000 | J22: =IF(C22="Treasury bond",I22*(G22+H22)/100,I22*G22) -> 23597.08 | K22: =IF($B$6=0,0,J22/$B$6) -> 0.078656933 | L22: WInS price checked against the curve (+14bp)
A23: 2042 | B23: T 3.125% 15-Nov-2041 | C23: Treasury bond | D23: 15 Nov 2041 | E23: 0.438835 | F23: =$B$9*E23 -> 21941.75 | G23: 76.367 | H23: 1.156 | I23: =IF(C23="Treasury bond",ROUNDUP(F23/((G23+H23)/100),-3),ROUNDUP(F23/G23,0)) -> 29000 | J23: =IF(C23="Treasury bond",I23*(G23+H23)/100,I23*G23) -> 22481.67 | K23: =IF($B$6=0,0,J23/$B$6) -> 0.0749389 | L23: WInS price checked against the curve (+15bp)
A24: Total | F24: =SUM(F14:F23) -> 290378.9 | J24: =SUM(J14:J23) -> 292257.1 | K24: =SUM(K14:K23) -> 0.97419033

Sheet Trade Log
A1: Trade # | B1: Date (US Eastern) | C1: Ticker | D1: Type | E1: Buy or sell | F1: Quantity (shares, or face value $ for bonds) | G1: Fill price (per share, or per $100 face) | H1: Accrued interest paid ($, bonds only) | I1: Commission ($) | J1: Gross amount ($) | K1: Cash impact ($) | L1: Job | M1: Trade note (copied exactly from WInS) | N1: Note length (characters) | O1: Within note limit | P1: Entered by | Q1: Screenshot saved
A2: =IF(C2="","",ROW()-1) | I2: =IF(C2="","",IF(D2="Treasury bond",CommBond,CommETF)) | J2: =IF(C2="","",IF(D2="Treasury bond",F2*G2/100,F2*G2)) | K2: =IF(C2="","",IF(E2="Buy",-(J2+N(H2)+I2),J2+N(H2)-I2)) | L2: =IF(C2="","",IFERROR(VLOOKUP(C2,PlanHoldings,2,FALSE),"Not in plan")) | N2: =IF(M2="","",LEN(M2)) | O2: =IF(OR(M2="",NoteLimit=""),"",IF(N2<=NoteLimit,"OK","Too long")) | Q2: FALSE
A3: =IF(C3="","",ROW()-1) | I3: =IF(C3="","",IF(D3="Treasury bond",CommBond,CommETF)) | J3: =IF(C3="","",IF(D3="Treasury bond",F3*G3/100,F3*G3)) | K3: =IF(C3="","",IF(E3="Buy",-(J3+N(H3)+I3),J3+N(H3)-I3)) | L3: =IF(C3="","",IFERROR(VLOOKUP(C3,PlanHoldings,2,FALSE),"Not in plan")) | N3: =IF(M3="","",LEN(M3)) | O3: =IF(OR(M3="",NoteLimit=""),"",IF(N3<=NoteLimit,"OK","Too long")) | Q3: FALSE
A4: =IF(C4="","",ROW()-1) | I4: =IF(C4="","",IF(D4="Treasury bond",CommBond,CommETF)) | J4: =IF(C4="","",IF(D4="Treasury bond",F4*G4/100,F4*G4)) | K4: =IF(C4="","",IF(E4="Buy",-(J4+N(H4)+I4),J4+N(H4)-I4)) | L4: =IF(C4="","",IFERROR(VLOOKUP(C4,PlanHoldings,2,FALSE),"Not in plan")) | N4: =IF(M4="","",LEN(M4)) | O4: =IF(OR(M4="",NoteLimit=""),"",IF(N4<=NoteLimit,"OK","Too long")) | Q4: FALSE
A5: =IF(C5="","",ROW()-1) | I5: =IF(C5="","",IF(D5="Treasury bond",CommBond,CommETF)) | J5: =IF(C5="","",IF(D5="Treasury bond",F5*G5/100,F5*G5)) | K5: =IF(C5="","",IF(E5="Buy",-(J5+N(H5)+I5),J5+N(H5)-I5)) | L5: =IF(C5="","",IFERROR(VLOOKUP(C5,PlanHoldings,2,FALSE),"Not in plan")) | N5: =IF(M5="","",LEN(M5)) | O5: =IF(OR(M5="",NoteLimit=""),"",IF(N5<=NoteLimit,"OK","Too long")) | Q5: FALSE
A6: =IF(C6="","",ROW()-1) | I6: =IF(C6="","",IF(D6="Treasury bond",CommBond,CommETF)) | J6: =IF(C6="","",IF(D6="Treasury bond",F6*G6/100,F6*G6)) | K6: =IF(C6="","",IF(E6="Buy",-(J6+N(H6)+I6),J6+N(H6)-I6)) | L6: =IF(C6="","",IFERROR(VLOOKUP(C6,PlanHoldings,2,FALSE),"Not in plan")) | N6: =IF(M6="","",LEN(M6)) | O6: =IF(OR(M6="",NoteLimit=""),"",IF(N6<=NoteLimit,"OK","Too long")) | Q6: FALSE
A7: =IF(C7="","",ROW()-1) | I7: =IF(C7="","",IF(D7="Treasury bond",CommBond,CommETF)) | J7: =IF(C7="","",IF(D7="Treasury bond",F7*G7/100,F7*G7)) | K7: =IF(C7="","",IF(E7="Buy",-(J7+N(H7)+I7),J7+N(H7)-I7)) | L7: =IF(C7="","",IFERROR(VLOOKUP(C7,PlanHoldings,2,FALSE),"Not in plan")) | N7: =IF(M7="","",LEN(M7)) | O7: =IF(OR(M7="",NoteLimit=""),"",IF(N7<=NoteLimit,"OK","Too long")) | Q7: FALSE
A8: =IF(C8="","",ROW()-1) | I8: =IF(C8="","",IF(D8="Treasury bond",CommBond,CommETF)) | J8: =IF(C8="","",IF(D8="Treasury bond",F8*G8/100,F8*G8)) | K8: =IF(C8="","",IF(E8="Buy",-(J8+N(H8)+I8),J8+N(H8)-I8)) | L8: =IF(C8="","",IFERROR(VLOOKUP(C8,PlanHoldings,2,FALSE),"Not in plan")) | N8: =IF(M8="","",LEN(M8)) | O8: =IF(OR(M8="",NoteLimit=""),"",IF(N8<=NoteLimit,"OK","Too long")) | Q8: FALSE
A9: =IF(C9="","",ROW()-1) | I9: =IF(C9="","",IF(D9="Treasury bond",CommBond,CommETF)) | J9: =IF(C9="","",IF(D9="Treasury bond",F9*G9/100,F9*G9)) | K9: =IF(C9="","",IF(E9="Buy",-(J9+N(H9)+I9),J9+N(H9)-I9)) | L9: =IF(C9="","",IFERROR(VLOOKUP(C9,PlanHoldings,2,FALSE),"Not in plan")) | N9: =IF(M9="","",LEN(M9)) | O9: =IF(OR(M9="",NoteLimit=""),"",IF(N9<=NoteLimit,"OK","Too long")) | Q9: FALSE
A10: =IF(C10="","",ROW()-1) | I10: =IF(C10="","",IF(D10="Treasury bond",CommBond,CommETF)) | J10: =IF(C10="","",IF(D10="Treasury bond",F10*G10/100,F10*G10)) | K10: =IF(C10="","",IF(E10="Buy",-(J10+N(H10)+I10),J10+N(H10)-I10)) | L10: =IF(C10="","",IFERROR(VLOOKUP(C10,PlanHoldings,2,FALSE),"Not in plan")) | N10: =IF(M10="","",LEN(M10)) | O10: =IF(OR(M10="",NoteLimit=""),"",IF(N10<=NoteLimit,"OK","Too long")) | Q10: FALSE
A11: =IF(C11="","",ROW()-1) | I11: =IF(C11="","",IF(D11="Treasury bond",CommBond,CommETF)) | J11: =IF(C11="","",IF(D11="Treasury bond",F11*G11/100,F11*G11)) | K11: =IF(C11="","",IF(E11="Buy",-(J11+N(H11)+I11),J11+N(H11)-I11)) | L11: =IF(C11="","",IFERROR(VLOOKUP(C11,PlanHoldings,2,FALSE),"Not in plan")) | N11: =IF(M11="","",LEN(M11)) | O11: =IF(OR(M11="",NoteLimit=""),"",IF(N11<=NoteLimit,"OK","Too long")) | Q11: FALSE
A12: =IF(C12="","",ROW()-1) | I12: =IF(C12="","",IF(D12="Treasury bond",CommBond,CommETF)) | J12: =IF(C12="","",IF(D12="Treasury bond",F12*G12/100,F12*G12)) | K12: =IF(C12="","",IF(E12="Buy",-(J12+N(H12)+I12),J12+N(H12)-I12)) | L12: =IF(C12="","",IFERROR(VLOOKUP(C12,PlanHoldings,2,FALSE),"Not in plan")) | N12: =IF(M12="","",LEN(M12)) | O12: =IF(OR(M12="",NoteLimit=""),"",IF(N12<=NoteLimit,"OK","Too long")) | Q12: FALSE
A13: =IF(C13="","",ROW()-1) | I13: =IF(C13="","",IF(D13="Treasury bond",CommBond,CommETF)) | J13: =IF(C13="","",IF(D13="Treasury bond",F13*G13/100,F13*G13)) | K13: =IF(C13="","",IF(E13="Buy",-(J13+N(H13)+I13),J13+N(H13)-I13)) | L13: =IF(C13="","",IFERROR(VLOOKUP(C13,PlanHoldings,2,FALSE),"Not in plan")) | N13: =IF(M13="","",LEN(M13)) | O13: =IF(OR(M13="",NoteLimit=""),"",IF(N13<=NoteLimit,"OK","Too long")) | Q13: FALSE
... A210: =IF(C210="","",ROW()-1) | I210: =IF(C210="","",IF(D210="Treasury bond",CommBond,CommETF)) | J210: =IF(C210="","",IF(D210="Treasury bond",F210*G210/100,F210*G210)) | K210: =IF(C210="","",IF(E210="Buy",-(J210+N(H210)+I210),J210+N(H210)-I210)) | L210: =IF(C210="","",IFERROR(VLOOKUP(C210,PlanHoldings,2,FALSE),"Not in plan")) | N210: =IF(M210="","",LEN(M210)) | O210: =IF(OR(M210="",NoteLimit=""),"",IF(N210<=NoteLimit,"OK","Too long")) | Q210: FALSE

Sheet TN Analysis
A1: Trading Notes Analysis: three picks
A2: Due Fri 23 Oct 2026, 5 pm ET (Sat 24 Oct, 8 am AEDT). Pick 3 real WInS trades. Notes must match WInS exactly; Wharton checks them. Reflections: up to 100 words each, written by the team.
A4: Pick | B4: Trade # | C4: Date | D4: Ticker | E4: Buy or sell | F4: Job | G4: Trade note (from Trade Log) | H4: Reflection (max 100 words) | I4: Word count | J4: Within 100 words | K4: Says why | L4: Fits the strategy | M4: Links to Laura's goals, funding or risk | N4: Owner
A5: 1 | C5: =IF($B5="","",IFERROR(INDEX('Trade Log'!B:B,MATCH($B5,'Trade Log'!$A:$A,0)),"Trade # not found")) | D5: =IF($B5="","",IFERROR(INDEX('Trade Log'!C:C,MATCH($B5,'Trade Log'!$A:$A,0)),"")) | E5: =IF($B5="","",IFERROR(INDEX('Trade Log'!E:E,MATCH($B5,'Trade Log'!$A:$A,0)),"")) | F5: =IF($B5="","",IFERROR(INDEX('Trade Log'!L:L,MATCH($B5,'Trade Log'!$A:$A,0)),"")) | G5: =IF($B5="","",IFERROR(INDEX('Trade Log'!M:M,MATCH($B5,'Trade Log'!$A:$A,0)),"")) | I5: =IF(TRIM(H5)="",0,LEN(TRIM(H5))-LEN(SUBSTITUTE(TRIM(H5)," ",""))+1) -> 0 | J5: =IF(H5="","",IF(I5<=100,"OK","Over 100")) | K5: FALSE | L5: FALSE | M5: FALSE
A6: 2 | C6: =IF($B6="","",IFERROR(INDEX('Trade Log'!B:B,MATCH($B6,'Trade Log'!$A:$A,0)),"Trade # not found")) | D6: =IF($B6="","",IFERROR(INDEX('Trade Log'!C:C,MATCH($B6,'Trade Log'!$A:$A,0)),"")) | E6: =IF($B6="","",IFERROR(INDEX('Trade Log'!E:E,MATCH($B6,'Trade Log'!$A:$A,0)),"")) | F6: =IF($B6="","",IFERROR(INDEX('Trade Log'!L:L,MATCH($B6,'Trade Log'!$A:$A,0)),"")) | G6: =IF($B6="","",IFERROR(INDEX('Trade Log'!M:M,MATCH($B6,'Trade Log'!$A:$A,0)),"")) | I6: =IF(TRIM(H6)="",0,LEN(TRIM(H6))-LEN(SUBSTITUTE(TRIM(H6)," ",""))+1) -> 0 | J6: =IF(H6="","",IF(I6<=100,"OK","Over 100")) | K6: FALSE | L6: FALSE | M6: FALSE
A7: 3 | C7: =IF($B7="","",IFERROR(INDEX('Trade Log'!B:B,MATCH($B7,'Trade Log'!$A:$A,0)),"Trade # not found")) | D7: =IF($B7="","",IFERROR(INDEX('Trade Log'!C:C,MATCH($B7,'Trade Log'!$A:$A,0)),"")) | E7: =IF($B7="","",IFERROR(INDEX('Trade Log'!E:E,MATCH($B7,'Trade Log'!$A:$A,0)),"")) | F7: =IF($B7="","",IFERROR(INDEX('Trade Log'!L:L,MATCH($B7,'Trade Log'!$A:$A,0)),"")) | G7: =IF($B7="","",IFERROR(INDEX('Trade Log'!M:M,MATCH($B7,'Trade Log'!$A:$A,0)),"")) | I7: =IF(TRIM(H7)="",0,LEN(TRIM(H7))-LEN(SUBSTITUTE(TRIM(H7)," ",""))+1) -> 0 | J7: =IF(H7="","",IF(I7<=100,"OK","Over 100")) | K7: FALSE | L7: FALSE | M7: FALSE

Sheet WInS Notes
A1: What WInS shows (read 29 Sep 2026, no orders placed)
A2: Read from the logged-in WInS account Caplet-10465936. Prices are 28 Sep 2026 closes as WInS displayed them (15-minute delayed data).
A4: Topic | B4: Finding | C4: Where seen | D4: What it means for us
A5: Trading window | B5: Trading started 28 Sep 2026 9:30 am ET and ends 6 Nov 2026 4:00 pm ET (39 days left on 29 Sep) | C5: Session Rules | D5: Matches the IPS deadline; the book is frozen on 6 Nov
A6: Starting cash | B6: $300,000; no weekly deposits; 0% interest on cash | C6: Session Rules | D6: Idle cash earns nothing, so keep cash near 1%
A7: Trades | B7: 200 allowed; 0 used. Open and cancelled orders do not count | C7: Session Rules; Portfolio FAQ | D7: The planned book needs about 4 to 5 trades
A8: Day trading, margin, short selling | B8: Not allowed | C8: Session Rules | D8: No change
A9: Security types | B9: Stocks and ETFs on many exchanges; bonds limited to US Treasury bonds | C9: Session Rules | D9: The bond page also lists UK, German, French and Dutch exchanges, but the rules allow US Treasuries only
A10: Minimum buy price | B10: 3 | C10: Session Rules | D10: The official Wharton guide says $5; all our ETFs are well above both
A11: Fractional shares | B11: Not allowed | C11: Session Rules | D11: Round share counts down
A12: Commission | B12: $25 per stock or ETF trade; $10 per bond trade | C12: Session Rules | D12: Matches the Portfolio tab
A13: Position limit | B13: Stocks and ETFs: 200% per position and per security. Bonds: 100% per security and for all bonds | C13: Session Rules | D13: No position-limit branch applies; the recommended book can be bought as planned
A14: Volume rule | B14: Orders can take at most half of a security's market volume; larger orders wait | C14: Portfolio FAQ | D14: Our largest order (TLH, about 1,375 shares) is far below half of 4.45m
A15: Fills | B15: US orders fill at real-time bid/ask; orders placed while the market is closed fill at the next open. Bonds fill at end-of-day prices | C15: Portfolio FAQ; trading page | D15: Place orders during US hours if you want a known price
A16: Trade note box | B16: 300-character maximum (maxlength on the note box) | C16: Trade Notes page | D16: Wharton's 413-character example would not fit. Draft notes to 300 characters or less
A17: Adding notes | B17: Notes are added in Preview Order and can also be added or viewed from Order History or Transaction History (Add/View Notes) | C17: Portfolio FAQ; Trade Notes page | D17: Whether a saved note can be edited later is not confirmed. Treat the first note as final
A18: 2032 Treasury | B18: Not listed. The WInS bond list has 43 US Treasuries; none mature between 15 Feb 2031 and 15 Feb 2036 | C18: Bonds page drop-down | D18: Use IBTM for the building minimum (research choice 2)
A19: Week 1 email | B19: Posted on the dashboard (26-27 Week-One-Email.pdf); opens as a download, not read here | C19: Dashboard | D19: Someone on the team should read it
A20: Market context | B20: WInS news on 28 Sep: 10-year Treasury yield above 5.25% | C20: IEF quote page news | D20: Higher yields make the Treasury ladder cheaper than the 25 Sep model price. Rerun the ladder cost before the IPS
A22: Ticker | B22: Name as shown in WInS | C22: Last close 28 Sep 2026 | D22: Volume 28 Sep 2026
A23: IEF | B23: iShares 7-10 Year Treasury Bond ETF | C23: 89.53 | D23: 11367342
A24: TLH | B24: iShares 10-20 Year Treasury Bond ETF | C24: 92.75 | D24: 4450770
A25: IBTM | B25: iShares iBonds Dec 2032 Term Treasury ETF | C25: 21.76 | D25: 268076
A26: VT | B26: Vanguard Total World Stock ETF | C26: 158.81 | D26: 2631243
A27: VGIT | B27: Vanguard Intermediate-Term Treasury ETF | C27: 56.7 | D27: 4616404
A28: SPTI | B28: State Street SPDR Portfolio Intermediate Term Treasury ETF | C28: 27.3 | D28: 3239327
A29: VTI | B29: Vanguard Morningstar Total Stock Market ETF | C29: 375.84 | D29: 3940404
A30: VXUS | B30: Vanguard Total International Stock ETF | C30: 85.75 | D30: 6666961
A31: TLT | B31: iShares 20+ Year Treasury Bond ETF | C31: 78.62 | D31: 63463430
A32: SPTL | B32: State Street SPDR Portfolio Long Term Treasury ETF | C32: 24.06 | D32: 15539399
A33: SGOV | B33: iShares 0-3 Month Treasury Bond ETF | C33: 100.67 | D33: 20998859

Sheet R&B Tickets
A1: RAB Tickets: Friday 2 Oct 2026 WInS orders (both books; the team's 1 Oct vote picks one)
A2: AI-generated by Claude Code (RAB Kit WS6) from rab/trades/tickets.csv. Nothing here places an order: students check and enter every order. Basis: 28 Sep 2026 closes; WInS bond prices from tab Book L. Friday: re-run refresh_tickets.py --basis friday and type the new prices into column K.
A3: Inputs (official rules / WInS Notes) | B3: Value
A4: Starting WInS cash ($) | B4: 300000
A5: Commission per stock or ETF trade ($) | B5: 25
A6: Commission per Treasury trade ($) | B6: 10
A7: Never let cash fall below ($, kit stop rule 4) | B7: 1000
A8: Max trades allowed in the competition | B8: 200
A9: Book | B9: Order | C9: Ticker or bond | D9: Type | E9: Exact WInS name to look for | F9: Name status | G9: CUSIP | H9: Serves (Laura's plan) | I9: Quantity | J9: Quantity unit | K9: Reference price | L9: Price as of | M9: Price source | N9: Accrued interest per $100 (bonds) | O9: Max price (do not pay above) | P9: Commission ($) | Q9: Expected cost incl. commission ($) | R9: Worst-case cost at max price ($) | S9: Kit Preview total ($, tickets.csv) | T9: Check: formula minus kit ($) | U9: Stop if Preview below ($) | V9: Stop if Preview above ($) | W9: Cash after: expected ($) | X9: Cash after: worst case ($) | Y9: Cash check | Z9: 30-day avg daily volume | AA9: Order size vs 2x daily volume | AB9: Trap to avoid | AC9: Alternate | AD9: Why this order | AE9: Worst-case accrued per $100 (bonds, if the fill slips to Mon 5 Oct)
A10: Portfolio | B10: 1 | C10: IBTR | D10: ETF | E10: iShares iBonds Dec 2036 Term Treasury ETF | F10: UNVERIFIED (issuer name) | H10: Jan 2037 payment | I10: 846 | J10: shares | K10: 23.49 | L10: 2026-09-28 | M10: iShares closing price 28 Sep (Nasdaq 23.485) | O10: 23.69 | P10: =IF(D10="Treasury",$B$6,$B$5) -> 25 | Q10: =IF(D10="Treasury",I10/100*(K10+N10),I10*K10)+P10 -> 19897.54 | R10: =IF(D10="Treasury",I10/100*(O10+AE10),I10*O10)+P10 -> 20066.74 | S10: 19897.54 | T10: =ROUND(Q10-S10,2) -> 0 | U10: 19698.565 | V10: 20096.515 | W10: =$B$4-SUMIFS($Q$10:Q10,$A$10:A10,A10) -> 280102.46 | X10: =$B$4-SUMIFS($R$10:R10,$A$10:A10,A10) -> 279933.26 | Y10: =IF(X10>=$B$7,"OK","STOP: below cash floor") -> OK | Z10: 52804.233 | AA10: =IF(Z10="","bond: n/a",I10/(2*Z10)) -> 0.0080107214 | AB10: Thinnest fund (about 1.6m shares outstanding). Check the name says Dec 2036. | AC10: IBTQ (ends a year early, the money waits); the 4.5% Feb-2036 bond only if its WInS price passes the yield check (stale on 29 Sep) | AD10: iBonds first (live prices, so cash is known at once); a small first order to learn the screen
A11: Portfolio | B11: 2 | C11: IBTQ | D11: ETF | E11: iShares iBonds Dec 2035 Term Treasury ETF | F11: UNVERIFIED (issuer name) | H11: Jan 2036 payment | I11: 886 | J11: shares | K11: 23.7 | L11: 2026-09-28 | M11: iShares closing price 28 Sep (Nasdaq 23.6951) | O11: 23.9 | P11: =IF(D11="Treasury",$B$6,$B$5) -> 25 | Q11: =IF(D11="Treasury",I11/100*(K11+N11),I11*K11)+P11 -> 21023.2 | R11: =IF(D11="Treasury",I11/100*(O11+AE11),I11*O11)+P11 -> 21200.4 | S11: 21023.2 | T11: =ROUND(Q11-S11,2) -> 0 | U11: 20812.968 | V11: 21233.432 | W11: =$B$4-SUMIFS($Q$10:Q11,$A$10:A11,A11) -> 259079.26 | X11: =$B$4-SUMIFS($R$10:R11,$A$10:A11,A11) -> 258732.86 | Y11: =IF(X11>=$B$7,"OK","STOP: below cash floor") -> OK | Z11: 86882.467 | AA11: =IF(Z11="","bond: n/a",I11/(2*Z11)) -> 0.0050988423 | AB11: Check the name says Dec 2035. | AC11: IBTP (ends a year early)
A12: Portfolio | B12: 3 | C12: IBTP | D12: ETF | E12: iShares iBonds Dec 2034 Term Treasury ETF | F12: UNVERIFIED (issuer name) | H12: Jan 2035 payment | I12: 921 | J12: shares | K12: 24.1 | L12: 2026-09-28 | M12: iShares closing price 28 Sep (Nasdaq 24.1006) | O12: 24.28 | P12: =IF(D12="Treasury",$B$6,$B$5) -> 25 | Q12: =IF(D12="Treasury",I12/100*(K12+N12),I12*K12)+P12 -> 22221.1 | R12: =IF(D12="Treasury",I12/100*(O12+AE12),I12*O12)+P12 -> 22386.88 | S12: 22221.1 | T12: =ROUND(Q12-S12,2) -> 0 | U12: 21998.889 | V12: 22443.311 | W12: =$B$4-SUMIFS($Q$10:Q12,$A$10:A12,A12) -> 236858.16 | X12: =$B$4-SUMIFS($R$10:R12,$A$10:A12,A12) -> 236345.98 | Y12: =IF(X12>=$B$7,"OK","STOP: below cash floor") -> OK | Z12: 94220.533 | AA12: =IF(Z12="","bond: n/a",I12/(2*Z12)) -> 0.0048874697 | AB12: Check the name says Dec 2034. | AC12: IBTO (ends a year early)
A13: Portfolio | B13: 4 | C13: IBTO | D13: ETF | E13: iShares iBonds Dec 2033 Term Treasury ETF | F13: UNVERIFIED (issuer name) | H13: Jan 2034 payment | I13: 1016 | J13: shares | K13: 23.02 | L13: 2026-09-28 | M13: iShares closing price 28 Sep (= Nasdaq consolidated close 23.015 rounded) | O13: 23.19 | P13: =IF(D13="Treasury",$B$6,$B$5) -> 25 | Q13: =IF(D13="Treasury",I13/100*(K13+N13),I13*K13)+P13 -> 23413.32 | R13: =IF(D13="Treasury",I13/100*(O13+AE13),I13*O13)+P13 -> 23586.04 | S13: 23413.32 | T13: =ROUND(Q13-S13,2) -> 0 | U13: 23179.187 | V13: 23647.453 | W13: =$B$4-SUMIFS($Q$10:Q13,$A$10:A13,A13) -> 213444.84 | X13: =$B$4-SUMIFS($R$10:R13,$A$10:A13,A13) -> 212759.94 | Y13: =IF(X13>=$B$7,"OK","STOP: below cash floor") -> OK | Z13: 211074.03 | AA13: =IF(Z13="","bond: n/a",I13/(2*Z13)) -> 0.0024067385 | AB13: NOT IBTN: in WInS, IBTN is INSCORP Inc (SEEN 29 Sep). Type IBTO and read the name. | AC13: IBTM (ends a year early)
A14: Portfolio | B14: 5 | C14: IBTM | D14: ETF | E14: iShares iBonds Dec 2032 Term Treasury ETF | F14: SEEN 2026-09-29 | H14: Jan 2033 payment + facility floor (both jobs in one holding) | I14: 4486 | J14: shares | K14: 21.76 | L14: 2026-09-28 | M14: WInS close (tab WInS Notes) | O14: 21.9 | P14: =IF(D14="Treasury",$B$6,$B$5) -> 25 | Q14: =IF(D14="Treasury",I14/100*(K14+N14),I14*K14)+P14 -> 97640.36 | R14: =IF(D14="Treasury",I14/100*(O14+AE14),I14*O14)+P14 -> 98268.4 | S14: 97640.36 | T14: =ROUND(Q14-S14,2) -> 0 | U14: 96663.956 | V14: 98616.764 | W14: =$B$4-SUMIFS($Q$10:Q14,$A$10:A14,A14) -> 115804.48 | X14: =$B$4-SUMIFS($R$10:R14,$A$10:A14,A14) -> 114491.54 | Y14: =IF(X14>=$B$7,"OK","STOP: below cash floor") -> OK | Z14: 186480.1 | AA14: =IF(Z14="","bond: n/a",I14/(2*Z14)) -> 0.012028093 | AB14: Largest order. Check the name says Dec 2032. | AC14: none dated: no WInS Treasury matures between Feb 2031 and Feb 2036 (SEEN 29 Sep); if it cannot be bought, keep the cash and retry next session
A15: Portfolio | B15: 6 | C15: T 3.125% 15-Nov-2041 | D15: Treasury | E15: U.S. Treasury bond 3.125% maturing 15 Nov 2041 | F15: UNVERIFIED (WInS string not recorded) | G15: 912810QT8 | H15: Jan 2042 payment | I15: 19000 | J15: face value $ (unit UNVERIFIED in WInS) | K15: 76.367 | L15: 2026-09-28 | M15: Sheet tab Book L (typed-in WInS 28 Sep clean + accrued) | N15: 1.1889 | O15: 77.239 | P15: =IF(D15="Treasury",$B$6,$B$5) -> 10 | Q15: =IF(D15="Treasury",I15/100*(K15+N15),I15*K15)+P15 -> 14745.621 | R15: =IF(D15="Treasury",I15/100*(O15+AE15),I15*O15)+P15 -> 14916.146 | S15: 14745.613 | T15: =ROUND(Q15-S15,2) -> 0.01 | U15: 14582.205 | V15: 14916.145 | W15: =$B$4-SUMIFS($Q$10:Q15,$A$10:A15,A15) -> 101058.86 | X15: =$B$4-SUMIFS($R$10:R15,$A$10:A15,A15) -> 99575.394 | Y15: =IF(X15>=$B$7,"OK","STOP: below cash floor") -> OK | AA15: =IF(Z15="","bond: n/a",I15/(2*Z15)) -> bond: n/a | AB15: Same date as the 2.000% Nov-2041: check the coupon. | AC15: 2.000% 15 Nov 2041 (912810TC2), if listed and within 25bp | AD15: bonds after the iBonds: WInS fills them at end-of-day prices | AE15: 1.2144
A16: Portfolio | B16: 7 | C16: T 4.250% 15-Nov-2040 | D16: Treasury | E16: U.S. Treasury bond 4.250% maturing 15 Nov 2040 | F16: UNVERIFIED (WInS string not recorded) | G16: 912810QL5 | H16: Jan 2041 payment | I16: 17000 | J16: face value $ (unit UNVERIFIED in WInS) | K16: 89.186 | L16: 2026-09-28 | M16: Sheet tab Book L (typed-in WInS 28 Sep clean + accrued) | N16: 1.6168 | O16: 90.107 | P16: =IF(D16="Treasury",$B$6,$B$5) -> 10 | Q16: =IF(D16="Treasury",I16/100*(K16+N16),I16*K16)+P16 -> 15446.476 | R16: =IF(D16="Treasury",I16/100*(O16+AE16),I16*O16)+P16 -> 15608.928 | S16: 15446.484 | T16: =ROUND(Q16-S16,2) -> -0.01 | U16: 15291.928 | V16: 15608.922 | W16: =$B$4-SUMIFS($Q$10:Q16,$A$10:A16,A16) -> 85612.383 | X16: =$B$4-SUMIFS($R$10:R16,$A$10:A16,A16) -> 83966.466 | Y16: =IF(X16>=$B$7,"OK","STOP: below cash floor") -> OK | AA16: =IF(Z16="","bond: n/a",I16/(2*Z16)) -> bond: n/a | AB16: Same date as the 1.375% Nov-2040: check the coupon. | AC16: 1.375% 15 Nov 2040 (912810ST6), if listed and within 25bp | AE16: 1.6514
A17: Portfolio | B17: 8 | C17: T 4.375% 15-Nov-2039 | D17: Treasury | E17: U.S. Treasury bond 4.375% maturing 15 Nov 2039 | F17: UNVERIFIED (WInS string not recorded) | G17: 912810QD3 | H17: Jan 2040 payment | I17: 18000 | J17: face value $ (unit UNVERIFIED in WInS) | K17: 91.363 | L17: 2026-09-28 | M17: Sheet tab Book L (typed-in WInS 28 Sep clean + accrued) | N17: 1.6644 | O17: 92.255 | P17: =IF(D17="Treasury",$B$6,$B$5) -> 10 | Q17: =IF(D17="Treasury",I17/100*(K17+N17),I17*K17)+P17 -> 16754.932 | R17: =IF(D17="Treasury",I17/100*(O17+AE17),I17*O17)+P17 -> 16921.936 | S17: 16754.932 | T17: =ROUND(Q17-S17,2) -> 0 | U17: 16587.383 | V17: 16922.482 | W17: =$B$4-SUMIFS($Q$10:Q17,$A$10:A17,A17) -> 68857.451 | X17: =$B$4-SUMIFS($R$10:R17,$A$10:A17,A17) -> 67044.53 | Y17: =IF(X17>=$B$7,"OK","STOP: below cash floor") -> OK | AA17: =IF(Z17="","bond: n/a",I17/(2*Z17)) -> bond: n/a | AB17: Not the 4.375% Feb-2038 (stale price on 29 Sep): check the maturity. | AC17: 4.500% 15 Aug 2039 (912810QC5), if listed and within 25bp | AE17: 1.7002
A18: Portfolio | B18: 9 | C18: T 4.500% 15-May-2038 | D18: Treasury | E18: U.S. Treasury bond 4.500% maturing 15 May 2038 | F18: UNVERIFIED (WInS string not recorded) | G18: 912810PX0 | H18: Jan 2039 payment | I18: 19000 | J18: face value $ (unit UNVERIFIED in WInS) | K18: 94.281 | L18: 2026-09-28 | M18: Sheet tab Book L (typed-in WInS 28 Sep clean + accrued) | N18: 1.712 | O18: 95.121 | P18: =IF(D18="Treasury",$B$6,$B$5) -> 10 | Q18: =IF(D18="Treasury",I18/100*(K18+N18),I18*K18)+P18 -> 18248.67 | R18: =IF(D18="Treasury",I18/100*(O18+AE18),I18*O18)+P18 -> 18415.319 | S18: 18248.662 | T18: =ROUND(Q18-S18,2) -> 0.01 | U18: 18066.175 | V18: 18431.148 | W18: =$B$4-SUMIFS($Q$10:Q18,$A$10:A18,A18) -> 50608.781 | X18: =$B$4-SUMIFS($R$10:R18,$A$10:A18,A18) -> 48629.211 | Y18: =IF(X18>=$B$7,"OK","STOP: below cash floor") -> OK | AA18: =IF(Z18="","bond: n/a",I18/(2*Z18)) -> bond: n/a | AB18: Not the 4.500% Feb-2036 or Aug-2039: check the maturity. Sheet accrued 0.530 is a typo (1.66 on 28 Sep, 1.71 on 2 Oct); use what WInS shows. | AC18: 4.375% 15 Feb 2038 (912810PW2) only if its WInS price passes the yield check (stale on 29 Sep); else 5.000% 15 May 2037 (912810PU6) | AE18: 1.7491
A19: Portfolio | B19: 10 | C19: T 4.750% 15-Feb-2037 | D19: Treasury | E19: U.S. Treasury bond 4.750% maturing 15 Feb 2037 | F19: UNVERIFIED (WInS string not recorded) | G19: 912810PT9 | H19: Jan 2038 payment | I19: 20000 | J19: face value $ (unit UNVERIFIED in WInS) | K19: 97.152 | L19: 2026-09-28 | M19: Sheet tab Book L (typed-in WInS 28 Sep clean + accrued) | N19: 0.6196 | O19: 97.919 | P19: =IF(D19="Treasury",$B$6,$B$5) -> 10 | Q19: =IF(D19="Treasury",I19/100*(K19+N19),I19*K19)+P19 -> 19564.32 | R19: =IF(D19="Treasury",I19/100*(O19+AE19),I19*O19)+P19 -> 19725.42 | S19: 19564.313 | T19: =ROUND(Q19-S19,2) -> 0.01 | U19: 19368.67 | V19: 19759.956 | W19: =$B$4-SUMIFS($Q$10:Q19,$A$10:A19,A19) -> 31044.461 | X19: =$B$4-SUMIFS($R$10:R19,$A$10:A19,A19) -> 28903.791 | Y19: =IF(X19>=$B$7,"OK","STOP: below cash floor") -> OK | AA19: =IF(Z19="","bond: n/a",I19/(2*Z19)) -> bond: n/a | AB19: Check the maturity says 2037. | AC19: 5.000% 15 May 2037 (912810PU6), if listed and within 25bp | AE19: 0.6581
A20: Portfolio | B20: 11 | C20: VT | D20: ETF | E20: Vanguard Total World Stock ETF | F20: SEEN 2026-09-29 | H20: Branch: the world stock fund (growth money) | I20: 164 | J20: shares | K20: 158.81 | L20: 2026-09-28 | M20: WInS close (tab WInS Notes) | O20: 161.18 | P20: =IF(D20="Treasury",$B$6,$B$5) -> 25 | Q20: =IF(D20="Treasury",I20/100*(K20+N20),I20*K20)+P20 -> 26069.84 | R20: =IF(D20="Treasury",I20/100*(O20+AE20),I20*O20)+P20 -> 26458.52 | S20: 26069.84 | T20: =ROUND(Q20-S20,2) -> 0 | U20: 25681.16 | V20: 26458.52 | W20: =$B$4-SUMIFS($Q$10:Q20,$A$10:A20,A20) -> 4974.621 | X20: =$B$4-SUMIFS($R$10:R20,$A$10:A20,A20) -> 2445.271 | Y20: =IF(X20>=$B$7,"OK","STOP: below cash floor") -> OK | Z20: 2223656.8 | AA20: =IF(Z20="","bond: n/a",I20/(2*Z20)) -> 3.6876194e-05 | AB20: Not VTI (U.S. only). Order 11: place it only in the session after all five bonds show Filled (Mon 5 Oct ET); re-run with --cash-before-vt first. | AC20: VTI + VXUS in VT's own U.S./non-U.S. mix (two trades) | AD20: last, in the next session: sized from the cash left after the bonds fill (payments and floor first)
A21: BookL | B21: 1 | C21: IBTR | D21: ETF | E21: iShares iBonds Dec 2036 Term Treasury ETF | F21: UNVERIFIED (issuer name) | H21: Jan 2037 payment | I21: 1252 | J21: shares | K21: 23.49 | L21: 2026-09-28 | M21: iShares closing price 28 Sep (Nasdaq 23.485) | O21: 23.69 | P21: =IF(D21="Treasury",$B$6,$B$5) -> 25 | Q21: =IF(D21="Treasury",I21/100*(K21+N21),I21*K21)+P21 -> 29434.48 | R21: =IF(D21="Treasury",I21/100*(O21+AE21),I21*O21)+P21 -> 29684.88 | S21: 29434.48 | T21: =ROUND(Q21-S21,2) -> 0 | U21: 29140.135 | V21: 29728.825 | W21: =$B$4-SUMIFS($Q$10:Q21,$A$10:A21,A21) -> 270565.52 | X21: =$B$4-SUMIFS($R$10:R21,$A$10:A21,A21) -> 270315.12 | Y21: =IF(X21>=$B$7,"OK","STOP: below cash floor") -> OK | Z21: 52804.233 | AA21: =IF(Z21="","bond: n/a",I21/(2*Z21)) -> 0.01185511 | AB21: Thinnest fund (about 1.6m shares outstanding). Check the name says Dec 2036. | AC21: IBTQ (ends a year early, the money waits); the 4.5% Feb-2036 bond only if its WInS price passes the yield check (stale on 29 Sep) | AD21: iBonds first (live prices, so cash is known at once); a small first order to learn the screen
A22: BookL | B22: 2 | C22: IBTQ | D22: ETF | E22: iShares iBonds Dec 2035 Term Treasury ETF | F22: UNVERIFIED (issuer name) | H22: Jan 2036 payment | I22: 1311 | J22: shares | K22: 23.7 | L22: 2026-09-28 | M22: iShares closing price 28 Sep (Nasdaq 23.6951) | O22: 23.9 | P22: =IF(D22="Treasury",$B$6,$B$5) -> 25 | Q22: =IF(D22="Treasury",I22/100*(K22+N22),I22*K22)+P22 -> 31095.7 | R22: =IF(D22="Treasury",I22/100*(O22+AE22),I22*O22)+P22 -> 31357.9 | S22: 31095.7 | T22: =ROUND(Q22-S22,2) -> 0 | U22: 30784.743 | V22: 31406.657 | W22: =$B$4-SUMIFS($Q$10:Q22,$A$10:A22,A22) -> 239469.82 | X22: =$B$4-SUMIFS($R$10:R22,$A$10:A22,A22) -> 238957.22 | Y22: =IF(X22>=$B$7,"OK","STOP: below cash floor") -> OK | Z22: 86882.467 | AA22: =IF(Z22="","bond: n/a",I22/(2*Z22)) -> 0.0075446753 | AB22: Check the name says Dec 2035. | AC22: IBTP (ends a year early)
A23: BookL | B23: 3 | C23: IBTP | D23: ETF | E23: iShares iBonds Dec 2034 Term Treasury ETF | F23: UNVERIFIED (issuer name) | H23: Jan 2035 payment | I23: 1362 | J23: shares | K23: 24.1 | L23: 2026-09-28 | M23: iShares closing price 28 Sep (Nasdaq 24.1006) | O23: 24.28 | P23: =IF(D23="Treasury",$B$6,$B$5) -> 25 | Q23: =IF(D23="Treasury",I23/100*(K23+N23),I23*K23)+P23 -> 32849.2 | R23: =IF(D23="Treasury",I23/100*(O23+AE23),I23*O23)+P23 -> 33094.36 | S23: 32849.2 | T23: =ROUND(Q23-S23,2) -> 0 | U23: 32520.708 | V23: 33177.692 | W23: =$B$4-SUMIFS($Q$10:Q23,$A$10:A23,A23) -> 206620.62 | X23: =$B$4-SUMIFS($R$10:R23,$A$10:A23,A23) -> 205862.86 | Y23: =IF(X23>=$B$7,"OK","STOP: below cash floor") -> OK | Z23: 94220.533 | AA23: =IF(Z23="","bond: n/a",I23/(2*Z23)) -> 0.0072277239 | AB23: Check the name says Dec 2034. | AC23: IBTO (ends a year early)
A24: BookL | B24: 4 | C24: IBTO | D24: ETF | E24: iShares iBonds Dec 2033 Term Treasury ETF | F24: UNVERIFIED (issuer name) | H24: Jan 2034 payment | I24: 1503 | J24: shares | K24: 23.02 | L24: 2026-09-28 | M24: iShares closing price 28 Sep (= Nasdaq consolidated close 23.015 rounded) | O24: 23.19 | P24: =IF(D24="Treasury",$B$6,$B$5) -> 25 | Q24: =IF(D24="Treasury",I24/100*(K24+N24),I24*K24)+P24 -> 34624.06 | R24: =IF(D24="Treasury",I24/100*(O24+AE24),I24*O24)+P24 -> 34879.57 | S24: 34624.06 | T24: =ROUND(Q24-S24,2) -> 0 | U24: 34277.819 | V24: 34970.301 | W24: =$B$4-SUMIFS($Q$10:Q24,$A$10:A24,A24) -> 171996.56 | X24: =$B$4-SUMIFS($R$10:R24,$A$10:A24,A24) -> 170983.29 | Y24: =IF(X24>=$B$7,"OK","STOP: below cash floor") -> OK | Z24: 211074.03 | AA24: =IF(Z24="","bond: n/a",I24/(2*Z24)) -> 0.0035603622 | AB24: NOT IBTN: in WInS, IBTN is INSCORP Inc (SEEN 29 Sep). Type IBTO and read the name. | AC24: IBTM (ends a year early)
A25: BookL | B25: 5 | C25: IBTM | D25: ETF | E25: iShares iBonds Dec 2032 Term Treasury ETF | F25: SEEN 2026-09-29 | H25: Jan 2033 payment | I25: 1678 | J25: shares | K25: 21.76 | L25: 2026-09-28 | M25: WInS close (tab WInS Notes) | O25: 21.9 | P25: =IF(D25="Treasury",$B$6,$B$5) -> 25 | Q25: =IF(D25="Treasury",I25/100*(K25+N25),I25*K25)+P25 -> 36538.28 | R25: =IF(D25="Treasury",I25/100*(O25+AE25),I25*O25)+P25 -> 36773.2 | S25: 36538.28 | T25: =ROUND(Q25-S25,2) -> 0 | U25: 36172.897 | V25: 36903.663 | W25: =$B$4-SUMIFS($Q$10:Q25,$A$10:A25,A25) -> 135458.28 | X25: =$B$4-SUMIFS($R$10:R25,$A$10:A25,A25) -> 134210.09 | Y25: =IF(X25>=$B$7,"OK","STOP: below cash floor") -> OK | Z25: 186480.1 | AA25: =IF(Z25="","bond: n/a",I25/(2*Z25)) -> 0.0044991396 | AB25: Largest order. Check the name says Dec 2032. | AC25: none dated: no WInS Treasury matures between Feb 2031 and Feb 2036 (SEEN 29 Sep); if it cannot be bought, keep the cash and retry next session
A26: BookL | B26: 6 | C26: T 3.125% 15-Nov-2041 | D26: Treasury | E26: U.S. Treasury bond 3.125% maturing 15 Nov 2041 | F26: UNVERIFIED (WInS string not recorded) | G26: 912810QT8 | H26: Jan 2042 payment | I26: 29000 | J26: face value $ (unit UNVERIFIED in WInS) | K26: 76.367 | L26: 2026-09-28 | M26: Sheet tab Book L (typed-in WInS 28 Sep clean + accrued) | N26: 1.1889 | O26: 77.239 | P26: =IF(D26="Treasury",$B$6,$B$5) -> 10 | Q26: =IF(D26="Treasury",I26/100*(K26+N26),I26*K26)+P26 -> 22501.211 | R26: =IF(D26="Treasury",I26/100*(O26+AE26),I26*O26)+P26 -> 22761.486 | S26: 22501.199 | T26: =ROUND(Q26-S26,2) -> 0.01 | U26: 22251.787 | V26: 22761.485 | W26: =$B$4-SUMIFS($Q$10:Q26,$A$10:A26,A26) -> 112957.07 | X26: =$B$4-SUMIFS($R$10:R26,$A$10:A26,A26) -> 111448.6 | Y26: =IF(X26>=$B$7,"OK","STOP: below cash floor") -> OK | AA26: =IF(Z26="","bond: n/a",I26/(2*Z26)) -> bond: n/a | AB26: Same date as the 2.000% Nov-2041: check the coupon. | AC26: 2.000% 15 Nov 2041 (912810TC2), if listed and within 25bp | AD26: bonds after the iBonds: WInS fills them at end-of-day prices | AE26: 1.2144
A27: BookL | B27: 7 | C27: T 4.250% 15-Nov-2040 | D27: Treasury | E27: U.S. Treasury bond 4.250% maturing 15 Nov 2040 | F27: UNVERIFIED (WInS string not recorded) | G27: 912810QL5 | H27: Jan 2041 payment | I27: 26000 | J27: face value $ (unit UNVERIFIED in WInS) | K27: 89.186 | L27: 2026-09-28 | M27: Sheet tab Book L (typed-in WInS 28 Sep clean + accrued) | N27: 1.6168 | O27: 90.107 | P27: =IF(D27="Treasury",$B$6,$B$5) -> 10 | Q27: =IF(D27="Treasury",I27/100*(K27+N27),I27*K27)+P27 -> 23618.728 | R27: =IF(D27="Treasury",I27/100*(O27+AE27),I27*O27)+P27 -> 23867.184 | S27: 23618.74 | T27: =ROUND(Q27-S27,2) -> -0.01 | U27: 23382.36 | V27: 23867.175 | W27: =$B$4-SUMIFS($Q$10:Q27,$A$10:A27,A27) -> 89338.341 | X27: =$B$4-SUMIFS($R$10:R27,$A$10:A27,A27) -> 87581.42 | Y27: =IF(X27>=$B$7,"OK","STOP: below cash floor") -> OK | AA27: =IF(Z27="","bond: n/a",I27/(2*Z27)) -> bond: n/a | AB27: Same date as the 1.375% Nov-2040: check the coupon. | AC27: 1.375% 15 Nov 2040 (912810ST6), if listed and within 25bp | AE27: 1.6514
A28: BookL | B28: 8 | C28: T 4.375% 15-Nov-2039 | D28: Treasury | E28: U.S. Treasury bond 4.375% maturing 15 Nov 2039 | F28: UNVERIFIED (WInS string not recorded) | G28: 912810QD3 | H28: Jan 2040 payment | I28: 27000 | J28: face value $ (unit UNVERIFIED in WInS) | K28: 91.363 | L28: 2026-09-28 | M28: Sheet tab Book L (typed-in WInS 28 Sep clean + accrued) | N28: 1.6644 | O28: 92.255 | P28: =IF(D28="Treasury",$B$6,$B$5) -> 10 | Q28: =IF(D28="Treasury",I28/100*(K28+N28),I28*K28)+P28 -> 25127.398 | R28: =IF(D28="Treasury",I28/100*(O28+AE28),I28*O28)+P28 -> 25377.904 | S28: 25127.399 | T28: =ROUND(Q28-S28,2) -> 0 | U28: 24876.125 | V28: 25378.673 | W28: =$B$4-SUMIFS($Q$10:Q28,$A$10:A28,A28) -> 64210.943 | X28: =$B$4-SUMIFS($R$10:R28,$A$10:A28,A28) -> 62203.516 | Y28: =IF(X28>=$B$7,"OK","STOP: below cash floor") -> OK | AA28: =IF(Z28="","bond: n/a",I28/(2*Z28)) -> bond: n/a | AB28: Not the 4.375% Feb-2038 (stale price on 29 Sep): check the maturity. | AC28: 4.500% 15 Aug 2039 (912810QC5), if listed and within 25bp | AE28: 1.7002
A29: BookL | B29: 9 | C29: T 4.500% 15-May-2038 | D29: Treasury | E29: U.S. Treasury bond 4.500% maturing 15 May 2038 | F29: UNVERIFIED (WInS string not recorded) | G29: 912810PX0 | H29: Jan 2039 payment | I29: 29000 | J29: face value $ (unit UNVERIFIED in WInS) | K29: 94.281 | L29: 2026-09-28 | M29: Sheet tab Book L (typed-in WInS 28 Sep clean + accrued) | N29: 1.712 | O29: 95.121 | P29: =IF(D29="Treasury",$B$6,$B$5) -> 10 | Q29: =IF(D29="Treasury",I29/100*(K29+N29),I29*K29)+P29 -> 27847.97 | R29: =IF(D29="Treasury",I29/100*(O29+AE29),I29*O29)+P29 -> 28102.329 | S29: 27847.957 | T29: =ROUND(Q29-S29,2) -> 0.01 | U29: 27569.478 | V29: 28126.437 | W29: =$B$4-SUMIFS($Q$10:Q29,$A$10:A29,A29) -> 36362.973 | X29: =$B$4-SUMIFS($R$10:R29,$A$10:A29,A29) -> 34101.187 | Y29: =IF(X29>=$B$7,"OK","STOP: below cash floor") -> OK | AA29: =IF(Z29="","bond: n/a",I29/(2*Z29)) -> bond: n/a | AB29: Not the 4.500% Feb-2036 or Aug-2039: check the maturity. Sheet accrued 0.530 is a typo (1.66 on 28 Sep, 1.71 on 2 Oct); use what WInS shows. | AC29: 4.375% 15 Feb 2038 (912810PW2) only if its WInS price passes the yield check (stale on 29 Sep); else 5.000% 15 May 2037 (912810PU6) | AE29: 1.7491
A30: BookL | B30: 10 | C30: T 4.750% 15-Feb-2037 | D30: Treasury | E30: U.S. Treasury bond 4.750% maturing 15 Feb 2037 | F30: UNVERIFIED (WInS string not recorded) | G30: 912810PT9 | H30: Jan 2038 payment | I30: 30000 | J30: face value $ (unit UNVERIFIED in WInS) | K30: 97.152 | L30: 2026-09-28 | M30: Sheet tab Book L (typed-in WInS 28 Sep clean + accrued) | N30: 0.6196 | O30: 97.919 | P30: =IF(D30="Treasury",$B$6,$B$5) -> 10 | Q30: =IF(D30="Treasury",I30/100*(K30+N30),I30*K30)+P30 -> 29341.48 | R30: =IF(D30="Treasury",I30/100*(O30+AE30),I30*O30)+P30 -> 29583.13 | S30: 29341.47 | T30: =ROUND(Q30-S30,2) -> 0.01 | U30: 29048.055 | V30: 29634.884 | W30: =$B$4-SUMIFS($Q$10:Q30,$A$10:A30,A30) -> 7021.493 | X30: =$B$4-SUMIFS($R$10:R30,$A$10:A30,A30) -> 4518.057 | Y30: =IF(X30>=$B$7,"OK","STOP: below cash floor") -> OK | AA30: =IF(Z30="","bond: n/a",I30/(2*Z30)) -> bond: n/a | AB30: Check the maturity says 2037. | AC30: 5.000% 15 May 2037 (912810PU6), if listed and within 25bp | AE30: 0.6581
A32: Summary by book | B32: Trades | C32: Commissions ($) | D32: Expected spend ($) | E32: Cash left: expected ($) | F32: Cash left: worst case ($) | G32: Share of the 200-trade limit
A33: Portfolio | B33: =COUNTIF($A$10:$A$30,"Portfolio") -> 11 | C33: =SUMIFS($P$10:$P$30,$A$10:$A$30,"Portfolio") -> 200 | D33: =SUMIFS($Q$10:$Q$30,$A$10:$A$30,"Portfolio") -> 295025.38 | E33: =$B$4-D33 -> 4974.621 | F33: =$B$4-SUMIFS($R$10:$R$30,$A$10:$A$30,"Portfolio") -> 2445.271 | G33: =B33/$B$8 -> 0.055
A34: BookL | B34: =COUNTIF($A$10:$A$30,"BookL") -> 10 | C34: =SUMIFS($P$10:$P$30,$A$10:$A$30,"BookL") -> 175 | D34: =SUMIFS($Q$10:$Q$30,$A$10:$A$30,"BookL") -> 292978.51 | E34: =$B$4-D34 -> 7021.493 | F34: =$B$4-SUMIFS($R$10:$R$30,$A$10:$A$30,"BookL") -> 4518.057 | G34: =B34/$B$8 -> 0.05
A35: Portfolio: order 11 (VT) is placed the session after all five bonds show Filled (Mon 5 Oct ET), sized from the cash WInS then shows (refresh_tickets.py --cash-before-vt).

Sheet R&B Notes
A1: RAB Notes: one row per trade. Team note = what you paste into the WInS Trade note box (max 300 characters).
A2: The exemplar is an EXAMPLE only: the team rewrites every note in its own words before trading. Column M counts the Team note live; it turns red above 300. Rows marked 'conditional' are for a trade only if its condition happens (see 'When it is used').
A3: Trade note box limit (characters) | B3: 300
A4: Book | B4: Order | C4: Note ID | D4: Ticker or bond | E4: When it is used | F4: Laura goal | G4: TN Analysis role | H4: TN Analysis pick | I4: Brief (facts the note may use) | J4: Label | K4: Exemplar note | L4: Exemplar characters | M4: Team note (write here) | N4: Team note characters | O4: Characters left | P4: Team note status | Q4: IPS lines it links to
A5: Portfolio | B5: 1 | C5: IBTR | D5: IBTR | E5: Friday order 1 (both books) | F5: future funding | G5: tested | H5: Pick 1 (tested) | I5: Serves: Laura's 5th payment, $50,000 on 1 Jan 2037 (2027 deposit). Facts: iShares iBonds Dec 2036 Term Treasury ETF: 4 Treasuries maturing in 2036; ends on or about 15 Dec 2036; pays income monthly (iShares, 28 Sep); the test this note records: before the first order, `refresh_tickets.py` prints what Laura's ten payments cost on 1 Jan 2027 at the latest yields, the fall in yields that would use up the room (the break-even) and the words to type for it. The IPS claims the cost is under $300,000 (28 Sep: about $292,000, laura.ladder.cost_2027_strips; break-even about a quarter of a percentage point, laura.ladder.breakeven_fall_bp_strips). The 14 Oct check re-runs it (october_trade.md trigger B); the reflection reports that result either way; the break-even moves a lot from day to day: 20.1bp on 24 Sep, 19.3bp on 25 Sep, 26.2bp on 28 Sep, 28.9bp on 29 Sep (m1_ladder on the home.treasury.gov par curves fetched 30 Sep; MODEL; only 28 Sep is locked). So the note uses Friday's figure in words, never the 28 Sep one by default; basis: the numbers.yaml zero-coupon (STRIPS) figures, with forward rates coming true (the 1 Jan 2027 forward). WS4's 22.8bp is the same STRIPS basis with yields unchanged instead (about $293,000): a different convention, not the buyable ladder. Under the adopted rule reading R1(a) her real ladder is the WInS-listed one; sized to pay exactly $50,000 a rung it costs about $289,200 today, within $100 of STRIPS (`rab/results/M2/bookL_basis_check.txt`), so its room is about the same. The Sheet's Book L costs about $292,900 only because it buys more than needed (about $507,000 at forward rates). Both conventions round to 'about a quarter'; WS1 locks them (request 9). Use one basis in the note, the reflection and the IPS; if it fails on Friday: do not stop. Buy orders 1-10 from the `--split-from-curve` ticket (more in the dated holdings, less VT): the IPS says the 2028 deposit completes the earliest payments, so less is left for the facility (friday_checklist.md; exemplar IBTR_F in s5); who absorbs a gap: the 2028 deposit tops up the earliest payments first, so no payment is missed and less is left for the facility. Which part shrinks depends on the floor's definition, which the team settles (s7 triage): read literally, the IPS ('repay the whole remainder as Laura's facility floor') lowers the floor by the whole gap and the stock fund by only about a fifth of it (the floor costs about $117,000 per $150,000, laura.floor_cost_2028; derived); the kit's model (`plan_split`, WS4 `D_pre2027_rate_hedge.md`) holds the floor at $150,000 and puts the gap on the stock fund. 'The facility gets less' is true on either reading. 'Latest payments first' is the IPS funding rule, not the order of WInS trades; thinnest fund: about $38m in assets (iShares, 28 Sep); place it after the first hour. Sizes: Portfolio #1: 846 shares, expected Preview total $19,897.54 (ticket), 6.6% of the book (numbers.yaml); Laura's plan: about $29,000 of her 2027 deposit buys this rung; if its income is reinvested at only 2%, it delivers about $46,000 of the $50,000 (reinvest.rung.IBTR, MODEL; appendix only, never in a note). IPS: "At September 2026 yields the ten payments cost less than $300,000." / "The January 2027 deposit buys the liability-hedging portfolio, latest payments first." / "A moderate fall in yields would leave some payments for the 2028 deposit to complete" One number: 'a quarter of a percentage point' (the fall in yields before 1 Jan 2027 that lifts the ten payments above $300,000; the note says 'over about', because the room is used up only past it). On Friday type the words the refresh prints for that day's break-even: under 22.5bp 'about a fifth', 22.5 to 30bp 'about a quarter', 30 to 37.5bp 'about a third' [laura.ladder.breakeven_fall_bp_strips (26.2bp, MODEL, 28 Sep curve, zero-coupon basis, forward convention); Friday's figure is the refresh line, written in the Trade Log and re-locked by WS1 (request 1). $50,000 and $300,000 are case facts]. Do not say: 'Laura's ten $50,000 payments cost under...' without 'Treasuries for' (reads as ten $50,000 payments under $300,000); 'her $300,000 deposit' without 'first' (the WInS book is also $300,000); 'stocks get less' or 'the floor gets less' alone (which part shrinks depends on the floor's definition; say 'the facility gets less'); 'Tested before this first order:' as an opening (it reads as a label written for the analysis); 'a fall of a quarter point leaves...' (a fall must be MORE than the break-even, and 'point' alone is a price point); 'any gap falls on her first payment' (a large fall reaches several of the earliest; the IPS says 'some payments'); that the fund pays a set $50,000; 'thin' or 'risky' about the holding; 'we buy the latest payments first' (the IPS funding rule, not the WInS trade order); nor any word in notes.md s2. Friday: Friday fact, inside the note: the curve date ('at 1 Oct yields'). The refresh prints 'ten payments cost $X on 1 Jan 2027', the break-even and the words for this note: read them aloud, write them in the Trade Log, and type the printed words in place of 'a quarter' if they differ. If X is above $300,000, type IBTR_F (s5) and follow 'If the IBTR test fails' in friday_checklist.md. Use the WInS name string for IBTR in the Trade Log. If IBTR cannot be bought, the order becomes IBTQ and this note changes. | J5: EXAMPLE - team rewrites | K5: At 1 Oct yields, Treasuries for Laura's ten $50,000 payments cost under her $300,000 first deposit; this Dec 2036 Treasury fund is future funding for the fifth. If yields fall over about a quarter of a percentage point by January, her 2028 deposit tops up the earliest; the facility gets less. | L5: =LEN(K5) -> 293 | N5: =LEN(M5) -> 0 | O5: =$B$3-N5 -> 300 | P5: =IF(N5=0,"empty",IF(N5>$B$3,"TOO LONG: cut "&(N5-$B$3)&" characters","OK")) -> empty | Q5: At September 2026 yields the ten payments cost less than $300,000. / The January 2027 deposit buys the liability-hedging portfolio, latest payments first. / A moderate fall in yields would leave some payments for the 2028 deposit to complete
A6: Portfolio | B6: 2 | C6: IBTQ | D6: IBTQ | E6: Friday order 2 (both books) | F6: future funding | G6: supported | I6: Serves: Laura's 4th payment, $50,000 on 1 Jan 2036 (2027 deposit). Facts: iShares iBonds Dec 2035 Term Treasury ETF: 4 Treasuries; ends on or about 15 Dec 2035; monthly income (iShares, 28 Sep); WInS lists no Treasury maturing between 15 Feb 2031 and 15 Feb 2036 (43 bonds in the drop-down, SEEN 29 Sep), so none in 2035: a dated fund of 2035 Treasuries is the closest fit for the 2036 payment; iShares says its iBonds funds "do not seek to return any predetermined amount" (IBTM product page, 28 Sep 2026): the whole payout is not fixed, not only what its income earns. Sizes: Portfolio #2: 886 shares, expected Preview total $21,023.20 (ticket), 7.0% of the book (numbers.yaml); Laura's plan: about $31,000 of her 2027 deposit buys this rung; if its income is reinvested at only 2%, it delivers about $47,000 of the $50,000 (reinvest.rung.IBTQ, MODEL; appendix only, never in a note). IPS: "Laura's 2027 deposit buys Treasuries maturing before each of her ten $50,000 payments." One number: none needed: the dated gap in the WInS bond list is the fact [tab WInS Notes, SEEN 29 Sep]. Do not say: that no Treasury matures in those years at all (notes do; WInS just does not list them); that the fund repays or delivers a set $50,000; 'what its income earns can vary' as the only limit (the whole payout is not fixed); 'between Feb 2031 and Feb 2036' (the 2031 start means nothing for a 2036 payment); nor any word in notes.md s2. Friday: Friday fact: the WInS name string for IBTQ, copied exactly; re-read the drop-down for the gap. | J6: EXAMPLE - team rewrites | K6: For future funding: the iShares iBonds Dec 2035 Term Treasury ETF is for the fourth of Laura's ten $50,000 residency payments, due 1 Jan 2036. WInS lists no Treasury bond maturing in 2035, so a dated fund of 2035 Treasuries is the closest fit. What it pays out is not fixed. | L6: =LEN(K6) -> 274 | N6: =LEN(M6) -> 0 | O6: =$B$3-N6 -> 300 | P6: =IF(N6=0,"empty",IF(N6>$B$3,"TOO LONG: cut "&(N6-$B$3)&" characters","OK")) -> empty | Q6: Laura's 2027 deposit buys Treasuries maturing before each of her ten $50,000 payments.
A7: Portfolio | B7: 3 | C7: IBTP | D7: IBTP | E7: Friday order 3 (both books) | F7: future funding | G7: supported | I7: Serves: Laura's 3rd payment, $50,000 on 1 Jan 2035 (2027 deposit). Facts: iShares iBonds Dec 2034 Term Treasury ETF: 4 Treasuries; ends on or about 15 Dec 2034; monthly income (iShares, 28 Sep); fair-price test: on 28 Sep the fund's price was 0.06% above the value of the Treasuries it holds (NAV $24.09, close $24.10; wins.ibond_checks.IBTP.premium_to_nav_pct). The note reports the latest published figure: the Premium/Discount iShares gives for the 1 Oct close, which sets the 1 Oct closing price against the 1 Oct NAV, so overnight rate moves do not blur it (a 2bp move shifts IBTP's value about 0.13%: effective duration 6.43 years, `rab/data/ishares/ibonds_facts.csv`, 28 Sep). The trade-date NAV appears only after the note is saved, so the note cannot claim it. The premium, not the fund's yield, is the test: a fund holding only Treasuries always yields about the Treasury curve; why it matters to Laura: the payments leave little room under her $300,000 first deposit (about $7,600, laura.ladder.headroom_2027_strips), so paying a premium for a fund would eat into it (reflection only). Sizes: Portfolio #3: 921 shares, expected Preview total $22,221.10 (ticket), 7.4% of the book (numbers.yaml); Laura's plan: about $33,000 of her 2027 deposit buys this rung; if its income is reinvested at only 2%, it delivers about $47,000 of the $50,000 (reinvest.rung.IBTP, MODEL; appendix only, never in a note). IPS: "Laura's 2027 deposit buys Treasuries maturing before each of her ten $50,000 payments." One number: 'almost exactly' (the fund's closing price against the value of its Treasuries, 1 Oct close) [wins.ibond_checks.IBTP.premium_to_nav_pct = 0.06 on 28 Sep; the 1 Oct figure is read on Friday morning and written in the Trade Log. A figure such as 'within 0.1%' needs the quote_as WS1 adds at the Friday re-lock (request 2)]. Do not say: 'her money' or 'Laura's money' for WInS cash (her deposit arrives in Jan 2027); 'bp'; that the yield is locked in for Laura; 'its yield was close to the Treasury curve, so the price was fair' (a Treasury fund's yield always is); 'on the trade date' (that day's value is published only after the note is saved); 'so we paid a fair price' (the check is of the 1 Oct close, not of the fill); nor any word in notes.md s2. Friday: Friday fact, inside the note: 'At the 1 Oct close'. On Friday morning read the Premium/Discount iShares publishes for the 1 Oct close on the IBTP page (or its 1 Oct closing price and NAV, and divide), and write it in the Trade Log with its date. If it is more than about 0.1% either way, write what you found instead. Copy the WInS name string for IBTP. | J7: EXAMPLE - team rewrites | K7: The iShares iBonds Dec 2034 Term Treasury ETF is future funding for Laura's $50,000 residency payment on 1 Jan 2035. At the 1 Oct close its price was almost exactly the value of the 2034 Treasuries it holds; its end value is not fixed. | L7: =LEN(K7) -> 235 | N7: =LEN(M7) -> 0 | O7: =$B$3-N7 -> 300 | P7: =IF(N7=0,"empty",IF(N7>$B$3,"TOO LONG: cut "&(N7-$B$3)&" characters","OK")) -> empty | Q7: Laura's 2027 deposit buys Treasuries maturing before each of her ten $50,000 payments.
A8: Portfolio | B8: 4 | C8: IBTO | D8: IBTO | E8: Friday order 4 (both books) | F8: future funding | G8: supported | I8: Serves: Laura's 2nd payment, $50,000 on 1 Jan 2034 (2027 deposit). Facts: iShares iBonds Dec 2033 Term Treasury ETF: 11 Treasuries; ends on or about 15 Dec 2033, when it pays out; monthly income (iShares, 28 Sep); trap: in WInS, IBTN is INSCORP Inc (SEEN 29 Sep); no iShares iBonds Treasury fund uses the ticker IBTN (iShares iBonds Treasury list, 30 Sep). The name check belongs in the Trade Log and in the Final Report's account of the team's experience, not in the note. Sizes: Portfolio #4: 1,016 shares, expected Preview total $23,413.32 (ticket), 7.8% of the book (numbers.yaml); Laura's plan: about $35,000 of her 2027 deposit buys this rung; if its income is reinvested at only 2%, it delivers about $48,000 of the $50,000 (reinvest.rung.IBTO, MODEL; appendix only, never in a note). IPS: "Laura's 2027 deposit buys Treasuries maturing before each of her ten $50,000 payments." One number: none needed [-]. Do not say: anything about IBTN in the note (record the check in the Trade Log); anything unkind about the other company; 'which then closes' (reads as the fund failing); 'its reinvested income can vary' as the only limit (the whole payout is not fixed); nor any word in notes.md s2. Friday: Type IBTO and IBTN once each; copy both names exactly as WInS shows them into the Trade Log. Friday fact: the WInS name string for IBTO. | J8: EXAMPLE - team rewrites | K8: Role: future funding. The iShares iBonds Dec 2033 Term Treasury ETF is for the second of Laura's ten $50,000 payments, on 1 Jan 2034. WInS lists no Treasury bond maturing in 2033, so we use a fund of 2033 Treasuries; the amount it pays out that December is not fixed. | L8: =LEN(K8) -> 267 | N8: =LEN(M8) -> 0 | O8: =$B$3-N8 -> 300 | P8: =IF(N8=0,"empty",IF(N8>$B$3,"TOO LONG: cut "&(N8-$B$3)&" characters","OK")) -> empty | Q8: Laura's 2027 deposit buys Treasuries maturing before each of her ten $50,000 payments.
A9: Portfolio | B9: 5 | C9: IBTM_P | D9: IBTM | E9: Friday order 5 (Portfolio book) | F9: risk management and future funding | G9: supported | H9: Alternate A (supported: the floor and co-sponsors) | I9: Serves: two jobs: Laura's 1st payment, $50,000 on 1 Jan 2033 (2027 deposit), and the facility floor, the least she plans to give the facility (2028 deposit). Facts: iShares iBonds Dec 2032 Term Treasury ETF (SEEN in WInS 29 Sep): 15 Treasuries; ends on or about 15 Dec 2032; monthly income (iShares, 28 Sep); WInS lists no Treasury maturing in 2032 (none between 15 Feb 2031 and 15 Feb 2036, SEEN 29 Sep), so the IPS floor sits in this fund, together with the 2033 payment. Under the adopted rule reading R1(a) Laura's real plan is limited to WInS-listed securities too, so this fund is her floor holding as well; a reflection says so in one clause (s6). Late-2032 Treasury notes (4.125% 15 Nov 2032, 91282CFV8; 3.75% 30 Nov 2032, 91282CPM7; 3.875% 31 Dec 2032, 91282CPQ8, one day before the payment; MSPD Table V, 31 Aug 2026) are an option only under reading (b); what it holds: 15 Treasuries maturing from 31 Jan to 30 Nov 2032; about 48% by weight matures by 31 May 2032 (`research/insight_v1/wins_now/S1_fund_holdings_snapshot.csv`, 24 Sep). So its money comes back across 2032 and waits inside the fund until about 15 Dec: 'It holds 2032 Treasuries' is exact, the IPS's 'Treasuries maturing in late 2032' is loose (s7); both jobs fall due in Jan 2033 and come from different deposits (the payment from 2027, the floor from 2028): neither ranks behind the other; iShares says its iBonds funds "do not seek to return any predetermined amount" (IBTM product page, 28 Sep 2026); the limit, measured: if its income is reinvested at only 2%, IBTM delivers about 97% of the curve case, the least exposure of any rung (reinvest.rung.IBTM at_2pct 48,192 / at_curve 49,856; M9). Quote it only after WS1 adds a quote_as (request 4); Portfolio tab: 32.5% of the book, of which 24.3 points are the floor; Laura's plan: the floor costs about $117,000 of her 2028 deposit at the 28 Sep 5-year yield (laura.floor_cost_2028, MODEL; never in a note). Sizes: Portfolio #5: 4,486 shares, expected Preview total $97,640.36 (ticket), 32.5% of the book (numbers.yaml); Laura's plan: about $37,000 of her 2027 deposit buys the 2033 payment rung; if its income is reinvested at only 2%, it delivers about $48,000 of the $50,000 (reinvest.rung.IBTM, MODEL; appendix only, never in a note). IPS: "Part of the remainder buys Treasuries maturing in late 2032 that, with coupons reinvested, repay the whole remainder as Laura's facility floor." / "Laura's 2027 deposit buys Treasuries maturing before each of her ten $50,000 payments." One number: none in the exemplar ('about a third of our WInS portfolio' is available if the team trims) [wins.portfolio.holdings_close_0928 IBTM weight 0.3254 (WInS book)]. Do not say: 'then' between the payment and the floor (both are due in Jan 2033, from different deposits); that it 'covers', 'repays' or 'holds' a dollar amount (never '$150,000' next to this holding: PM-15); 'late-2032 Treasuries' for what it holds (they mature across 2032); two colons in one sentence, or a parenthesis that splits 'the facility floor ... she can name'; any 2031 dollar figure: range, top or co-sponsor amount (TN guide: not expected yet); the idea of the 2031 range is welcome; 'facility floor' without its gloss (the TN Analysis is read before the IPS); nor any word in notes.md s2. Friday: Re-read the WInS bond list for a 2032 Treasury (if one appears, tell Ray before trading). Friday fact: the WInS name string (SEEN 29 Sep; re-read it). A dated Preview price as the one number ('Bought at $__.__ on 2 Oct', the price WInS shows, never a kit reference price) fits only if the team trims elsewhere. If the team adopted the backstop sentence at the 1 Oct vote, type IBTM_R (s5) instead. | J9: EXAMPLE - team rewrites | K9: Future funding and risk management: the iShares iBonds Dec 2032 Term Treasury ETF has two jobs in Laura's plan, her first $50,000 payment and the facility floor, the least she plans to give, which she can name to co-sponsors in 2031. It holds 2032 Treasuries; its end value is not fixed. | L9: =LEN(K9) -> 287 | N9: =LEN(M9) -> 0 | O9: =$B$3-N9 -> 300 | P9: =IF(N9=0,"empty",IF(N9>$B$3,"TOO LONG: cut "&(N9-$B$3)&" characters","OK")) -> empty | Q9: Part of the remainder buys Treasuries maturing in late 2032 that, with coupons reinvested, repay the whole remainder as Laura's facility floor. / Laura's 2027 deposit buys Treasuries maturing before each of her ten $50,000 payments.
A10: Portfolio | B10: 6 | C10: T41 | D10: T 3.125% 15-Nov-2041 | E10: Friday order 6, first bond (both books) | F10: future funding | G10: supported | H10: Alternate C (supported: why bonds for the last five payments) | I10: Serves: Laura's 10th and last payment, $50,000 on 1 Jan 2042 (2027 deposit). Facts: U.S. Treasury bond 3.125% due 15 Nov 2041, CUSIP 912810QT8; matures 47 days before the payment; coupons twice a year; no iBonds Treasury fund ends from Dec 2037 to Dec 2043 (the list ends Dec 2036, then Dec 2044; iShares, 30 Sep), so the 2038-2042 payments use individual bonds; same-date alternate 2.000% 15 Nov 2041 (912810TC2, MSPD): the 1 Oct rule is the same as for Nov 2040: listed and inside its 25bp band means swap on Friday (SW41). Aug-maturity low coupons (1.125% Aug 2040, 1.75% Aug 2041) are not same-date alternates; in Laura's plan its set coupons plus principal come to about 86% of the $50,000 (reinvest.rung at_0pct 43,047); the rest depends on reinvested coupons (appendix only); WInS price 76.367 (28 Sep) is 1.9bp from the curve: passes. Sizes: Portfolio #6: $19,000 face, expected Preview total $14,745.61 (ticket), 4.9% of the book (numbers.yaml); Laura's plan: about $22,000 of her 2027 deposit buys this rung; if its income is reinvested at only 2%, it delivers about $45,000 of the $50,000 (reinvest.rung.T_3.125%_15-Nov-2041, MODEL; appendix only, never in a note). IPS: "Laura's 2027 deposit buys Treasuries maturing before each of her ten $50,000 payments." One number: none needed [-]. Do not say: 'each with a set amount due at maturity' (reads as a set $50,000; the face is about $29,000 in Book L); that the bond delivers a fixed $50,000 including coupons; 'between 2037 and 2043' (does 2037 count?); nor any word in notes.md s2. Friday: Price inside the 25bp band; if the 2.000% Nov-2041 is listed and passes, type SW41 instead. If WInS lists no 2.000% Nov 2041, the team may add 'WInS lists no lower-coupon bond of that date' if it fits. Friday fact: the WInS name string for the bond. | J10: EXAMPLE - team rewrites | K10: Role: future funding. The 3.125% Treasury bond maturing 15 Nov 2041 is for the last of Laura's ten $50,000 payments, on 1 Jan 2042. No iBonds Treasury fund ends from 2037 to 2043, so her last five payments use individual bonds; part of each payment comes from reinvested coupons. | L10: =LEN(K10) -> 279 | N10: =LEN(M10) -> 0 | O10: =$B$3-N10 -> 300 | P10: =IF(N10=0,"empty",IF(N10>$B$3,"TOO LONG: cut "&(N10-$B$3)&" characters","OK")) -> empty | Q10: Laura's 2027 deposit buys Treasuries maturing before each of her ten $50,000 payments.
A11: Portfolio | B11: 7 | C11: T40b | D11: T 4.250% 15-Nov-2040 | E11: Friday order 7 (both books), default: WInS does not list the 1.375% Nov-2040 | F11: future funding | G11: supported | I11: Serves: Laura's 9th payment, $50,000 on 1 Jan 2041 (2027 deposit). Facts: U.S. Treasury bond 4.250% due 15 Nov 2040, CUSIP 912810QL5; WInS price 89.186 (28 Sep) is 5.1bp from the curve: passes; same-date alternate 1.375% 15 Nov 2040 (912810ST6): it exists (MSPD Table V, 31 Aug 2026); its WInS listing is UNVERIFIED until the Friday drop-down read. About 38% of the 4.250% bond's cash before 2041 comes as coupons, against 17% (M9, MODEL; not in numbers.yaml); which note (the 1 Oct rule, one rule for all same-slot alternates): T40b if WInS does not list the 1.375%; SW40 if it is listed and its price passes the 25bp check; T40s if it is listed but its price fails. T40 and T40c are retired (T40c kept a better listed bond for October: a staged trade); T40b records a constraint, not a change, so it is not a 'refined' pick; pick 2 then goes to IBTM_R or the T39 fallback (s6); the price the team checks on Friday morning is the 1 Oct close (WInS shows the previous close; bonds fill at end-of-day prices), so the note dates it; record the fill price in the Trade Log. Sizes: Portfolio #7: $17,000 face, expected Preview total $15,446.48 (ticket), 5.1% of the book (numbers.yaml); Laura's plan: about $24,000 of her 2027 deposit buys this rung; if its income is reinvested at only 2%, it delivers about $45,000 of the $50,000 (reinvest.rung.T_4.250%_15-Nov-2040, MODEL; appendix only, never in a note). IPS: "Laura's 2027 deposit buys Treasuries maturing before each of her ten $50,000 payments." One number: none from numbers.yaml; the M9 coupon shares (38% vs 17%) need a numbers.yaml entry before any note uses them [M9_selection.md (MODEL)]. Do not say: 'less income to reinvest' (reads as a loss: say less of her payment rests on reinvested coupons); 'we are checking' (the drop-down read settles it before the order); that a swap will happen; nor any word in notes.md s2. Friday: Read the drop-down first (Thursday's full list read settles it in advance). Not listed: this note. Listed and passing: SW40. Listed but failing: T40s. Friday fact, inside: 'Its 1 Oct WInS price passed our curve check'. | J11: EXAMPLE - team rewrites | K11: Future funding: the 4.250% Treasury bond maturing 15 Nov 2040 is for Laura's ninth $50,000 payment, on 1 Jan 2041. A lower-coupon bond of that date would leave less of her payment resting on reinvested coupons, but WInS does not list one. Its 1 Oct WInS price passed our curve check. | L11: =LEN(K11) -> 283 | N11: =LEN(M11) -> 0 | O11: =$B$3-N11 -> 300 | P11: =IF(N11=0,"empty",IF(N11>$B$3,"TOO LONG: cut "&(N11-$B$3)&" characters","OK")) -> empty | Q11: Laura's 2027 deposit buys Treasuries maturing before each of her ten $50,000 payments.
A12: Portfolio | B12: 8 | C12: T39 | D12: T 4.375% 15-Nov-2039 | E12: Friday order 8 (both books) | F12: future funding | G12: supported | H12: Alternate B (supported: certainty and the reinvestment discovery); pick 2 if no refined note exists | I12: Serves: Laura's 8th payment, $50,000 on 1 Jan 2040 (2027 deposit). Facts: U.S. Treasury bond 4.375% due 15 Nov 2039, CUSIP 912810QD3; matures 47 days (about seven weeks) before the payment; WInS price 91.363 (28 Sep) is 6.6bp from the curve: passes; the certainty note: the one that says what Laura is owed and what she is not. In her plan the rung is about $25,000 of this bond; its set coupons plus principal come to about 86% of the $50,000 (reinvest.rung.T_4.375%_15-Nov-2039 at_0pct 42,947) and the rest depends on reinvested coupons: at 2% it falls about $4,700 short (at_2pct 45,320), at its own yield it just covers (at_own 50,203); scale: the Portfolio book holds $18,000 face (about 57% of $50,000 with coupons), so 'most of that payment' is true only in her plan, and the note says 'in her plan'; trap: WInS also lists a 4.375% bond of 15 Feb 2038, with a stale price; pick by coupon AND date. Sizes: Portfolio #8: $18,000 face, expected Preview total $16,754.93 (ticket), 5.6% of the book (numbers.yaml); Laura's plan: about $25,000 of her 2027 deposit buys this rung; if its income is reinvested at only 2%, it delivers about $45,000 of the $50,000 (reinvest.rung.T_4.375%_15-Nov-2039, MODEL; appendix only, never in a note). IPS: "In January 2033 the hedging portfolio becomes the operating reserve, held to maturity and shrinking as each holding pays out." One number: 'most of' (the share of the payment owed as set coupons and principal); 'about seven weeks' is date arithmetic [reinvest.rung.T_4.375%_15-Nov-2039 at_0pct 42,947 of 50,000 (MODEL); a percentage needs a quote_as from WS1 first (request 11)]. Do not say: 'the U.S. government owes a set amount' on its own (reads as the whole $50,000); 'reinvesting coupons covers the rest' (false at 2%: about $45,300 of $50,000); 'cover most of that payment' without 'in her plan' (the WInS holding is $18,000 face); that its price cannot fall (it can); 'we hold it to maturity' about WInS (the WInS book freezes on 6 Nov; holding to maturity is Laura's plan); nor any word in notes.md s2. Friday: Price inside the 25bp band. Friday fact: the WInS name string for the bond. | J12: EXAMPLE - team rewrites | K12: Future funding: the 4.375% Treasury bond maturing 15 Nov 2039 ends about seven weeks before Laura's $50,000 residency payment on 1 Jan 2040. Its price will move, but in her plan, held to maturity, its set coupons and principal cover most of it; the rest depends on reinvested coupons. | L12: =LEN(K12) -> 284 | N12: =LEN(M12) -> 0 | O12: =$B$3-N12 -> 300 | P12: =IF(N12=0,"empty",IF(N12>$B$3,"TOO LONG: cut "&(N12-$B$3)&" characters","OK")) -> empty | Q12: In January 2033 the hedging portfolio becomes the operating reserve, held to maturity and shrinking as each holding pays out.
A13: Portfolio | B13: 9 | C13: T38 | D13: T 4.500% 15-May-2038 | E13: Friday order 9 (both books) | F13: future funding | G13: supported | I13: Serves: Laura's 7th payment, $50,000 on 1 Jan 2039 (2027 deposit). Facts: U.S. Treasury bond 4.500% due 15 May 2038, CUSIP 912810PX0: the latest Treasury bond maturing before the payment (MSPD Table V, M9); it ends about 7.6 months early (231 days), and in Laura's plan that money waits in Treasury bills (0% in WInS); price check: this bond 14.4bp from the curve (passes). The 4.375% Feb 2038 bond at 99.98 (the 28 Sep close, seen in WInS 29 Sep) was 92bp off and the 4.5% Feb 2036 at 102.95 was 111bp off (both stale). The Feb 2038 bond was only the runner-up and ends earlier, so the check did not change the choice; why a 25bp band: the five good prices sat 2 to 15 hundredths of a percentage point of yield from the curve and the stale ones 92 and 111 hundredths (wins.bond_check.*), so a quarter point separates them; the Sheet records this bond's accrued interest as 0.530; 1.66 is right on 28 Sep (1.71 on 2 Oct): fix before 6 Nov; no longer a Trading Notes Analysis alternate (judge panel round 3: it tested WInS data, not her plan). The stale-price story, with the IBTN trap, goes in the Final Report's account of the competition and in the Trade Log, not in this note. Sizes: Portfolio #9: $19,000 face, expected Preview total $18,248.66 (ticket), 6.0% of the book (numbers.yaml); Laura's plan: about $28,000 of her 2027 deposit buys this rung; if its income is reinvested at only 2%, it delivers about $47,000 of the $50,000 (reinvest.rung.T_4.500%_15-May-2038, MODEL; appendix only, never in a note). IPS: "Laura's 2027 deposit buys Treasuries maturing before each of her ten $50,000 payments." / "At September 2026 yields the ten payments cost less than $300,000." One number: none: 'about seven and a half months' is date arithmetic (15 May 2038 to 1 Jan 2039 = 231 days). 'Almost a full percentage point of yield' (the stale gap) is available once WS1 aligns its quote_as (request 3) [wins.bond_check.T_4.375%_15-Feb-2038 gap_bp -92.1 (MODEL)]. Do not say: that WInS is 'wrong' or 'broken' (say 'stale'); 'bp'; '1 point of yield' (reads as a price point); the stale price of another bond (it did not change this choice; it goes in the Trade Log); 'is the last before' without a noun or verb after 'last'; the Sheet's accrued-interest typo; nor any word in notes.md s2. Friday: Re-check both prices on Friday and record any stale one in the Trade Log. Friday fact, inside: 'Its 1 Oct WInS price passed our curve check'. | J13: EXAMPLE - team rewrites | K13: Role: future funding. The 4.500% Treasury bond maturing 15 May 2038 is the last to mature before Laura's $50,000 residency payment on 1 Jan 2039, so in her plan its money waits about seven and a half months in Treasury bills. Its 1 Oct WInS price passed our curve check. | L13: =LEN(K13) -> 270 | N13: =LEN(M13) -> 0 | O13: =$B$3-N13 -> 300 | P13: =IF(N13=0,"empty",IF(N13>$B$3,"TOO LONG: cut "&(N13-$B$3)&" characters","OK")) -> empty | Q13: Laura's 2027 deposit buys Treasuries maturing before each of her ten $50,000 payments. / At September 2026 yields the ten payments cost less than $300,000.
A14: Portfolio | B14: 10 | C14: T37 | D14: T 4.750% 15-Feb-2037 | E14: Friday order 10, last bond (both books), if WInS does not list the 5.000% May 2037 | F14: future funding | G14: supported | I14: Serves: Laura's 6th payment, $50,000 on 1 Jan 2038 (2027 deposit). Facts: U.S. Treasury bond 4.750% due 15 Feb 2037, CUSIP 912810PT9; matures about 10.5 months (320 days) before the payment; in Laura's plan the money waits in Treasury bills (0% in WInS); WInS price 97.152 (28 Sep) is 15.3bp from the curve: passes. Its max price is now capped at the band top (97.919; it was 97.940, above the band); the only later bond before the payment is the 5.000% 15 May 2037 (912810PU6; MSPD Table V; WInS listing UNVERIFIED). The 1 Oct rule: listed and inside its band means swap on Friday (SW37): it ends three months nearer the payment and M9 finds the same share at 2% (90.5% each, MODEL). M9's 1.2% cost gap compares a model price with a WInS price 15bp rich, so it is not a reason on its own. Sizes: Portfolio #10: $20,000 face, expected Preview total $19,564.31 (ticket), 6.5% of the book (numbers.yaml); Laura's plan: about $29,000 of her 2027 deposit buys this rung; if its income is reinvested at only 2%, it delivers about $47,000 of the $50,000 (reinvest.rung.T_4.750%_15-Feb-2037, MODEL; appendix only, never in a note). IPS: "Laura's 2027 deposit buys Treasuries maturing before each of her ten $50,000 payments." / "In January 2033 the hedging portfolio becomes the operating reserve, held to maturity and shrinking as each holding pays out." One number: 'about ten and a half months early' (date arithmetic) [15 Feb 2037 to 1 Jan 2038 = 320 days]. Do not say: that the waiting money earns interest in WInS (WInS cash earns 0%); 'about ten months' (it is 10.5); 'comes out about the same' (an untraced comparison); nor any word in notes.md s2. Friday: Read the drop-down: 5.000% May 2037 listed and passing: type SW37. Listed but failing: replace 'It is the last WInS bond maturing before then' with 'The 5.000% May 2037 bond's WInS price failed our check'. Not listed: this note. Price inside the 25bp band; the last bond order. Friday fact: the WInS name string. | J14: EXAMPLE - team rewrites | K14: For future funding, the 4.750% Treasury bond maturing 15 Feb 2037 is for Laura's $50,000 payment on 1 Jan 2038. It is the last WInS bond maturing before then, so it ends about ten and a half months early; what the waiting money and its coupons earn can vary. | L14: =LEN(K14) -> 258 | N14: =LEN(M14) -> 0 | O14: =$B$3-N14 -> 300 | P14: =IF(N14=0,"empty",IF(N14>$B$3,"TOO LONG: cut "&(N14-$B$3)&" characters","OK")) -> empty | Q14: Laura's 2027 deposit buys Treasuries maturing before each of her ten $50,000 payments. / In January 2033 the hedging portfolio becomes the operating reserve, held to maturity and shrinking as each holding pays out.
A15: Portfolio | B15: 11 | C15: VT | D15: VT | E15: Order 11, the session after the bonds fill (Portfolio only) | F15: growth | G15: supported | H15: Pick 3 (supported) | I15: Serves: the return-seeking portfolio: growth for Laura's 2033 facility contribution above the floor. Facts: Vanguard Total World Stock ETF (SEEN in WInS 29 Sep): one global index fund of about 10,000 stocks at a 0.06% fee (M9); order 11, placed Mon 5 Oct ET once the five bonds show Filled, sized from the cash then left (`--cash-before-vt`). WInS Order History then shows the payments and the floor bought before any stocks, as the IPS says; the note no longer says 'bought last' (Order History shows it), so its characters carry the research: 'thousands of companies worldwide' (IPS: 'a global index fund of thousands of companies'); in Laura's plan the stock fund is all that is left after the payments and the floor (plan split ladder 66%, floor 25%, stock fund 9%, laura.plan_split_2028.strips). In WInS about 1.7% stays as cash for fees and rounding, which is why the note says 'Laura's plan'; why so little stock (reflection): the ten payments use almost all of Laura's first deposit (about $292,000 of $300,000 on 1 Jan 2027, laura.ladder.cost_2027_strips); research for the reflection: WS3 compared VT with a U.S.-only fund, a two-fund split and gold or property tilts; no alternative moved her bad case by more than about $1,500 (`D_fund_choice.md`; quote only after WS1 merges numbers_ws3.yaml, request 10); Laura's tolerance: 'willing to take thoughtful risks' (Client Profile p.2); the IPS rates it above average for facility money above the floor; IPS range: from the floor to the floor plus half the fund's value in 2031; the other half stays with Laura as a cushion; the 2033 contribution is capped at the announced top, so a rise after 2031 stays with her. A rise before 2031 lifts only the top of the range; the floor does not move; the tradeoff (reflection): more stock would raise her expected gift a little but lower the floor she names to co-sponsors in 2031 (IPS: moving money from the floor into equities 'widens the range of results. We do not recommend it'). Sizes: Portfolio #11: 164 shares, expected Preview total $26,069.84 (ticket), 8.7% of the book (numbers.yaml). IPS: "The rest, plus any 2027 remainder, forms the return-seeking portfolio, a global index fund of thousands of companies held to 2033." / "A market decline can reduce the facility contribution, but not below the floor." / "In 2031 Laura will give co-sponsors a range from the floor to the floor plus half the equity fund's value then." / "The other half remains with Laura as a cushion if costs rise or co-sponsors fall short." One number: none: 'thousands of companies' is the IPS's own description; 'about 9% of our WInS portfolio' (wins.portfolio.split_close_0928 vt 0.0868) moves to the reflection [IPS snapshot 30 Sep ('a global index fund of thousands of companies'; 'the floor plus half the equity fund's value')]. Do not say: 'only' before what a fall cuts (a fall also cuts the half she keeps); 'a rise lifts the top' without 'before 2031' (after 2031 the contribution is capped); 'lifts the range' (only the top moves; the floor does not); 'Half the fund stays hers' (drops its purpose, her cushion; with IBTM_R featured, that half also has a job); 'gets what was left' about WInS (about 1.7% stays as cash; say 'Laura's plan'); a return forecast (the IPS's 'should outperform' belongs in the IPS, not a note); probabilities, CAPE or valuation calls; 'Laura likes risk'; any 2031 or 2033 dollar figure; 'bought last' (Order History already shows it, and it is false if VT went in before the bonds by mistake); nor any word in notes.md s2. Friday: Mon 5 Oct: VT's size after `--cash-before-vt` (add `--split-from-curve` if the IBTR test failed). Friday fact: the WInS name string (SEEN 29 Sep; re-read it). | J15: EXAMPLE - team rewrites | K15: Growth: the Vanguard Total World Stock ETF, thousands of companies worldwide, gets what Laura's plan leaves after the payments and facility floor (the least she plans to give). A fall can cut her gift, not below the floor; a rise before 2031 lifts the top of the range co-sponsors hear. | L15: =LEN(K15) -> 286 | N15: =LEN(M15) -> 0 | O15: =$B$3-N15 -> 300 | P15: =IF(N15=0,"empty",IF(N15>$B$3,"TOO LONG: cut "&(N15-$B$3)&" characters","OK")) -> empty | Q15: The rest, plus any 2027 remainder, forms the return-seeking portfolio, a global index fund of thousands of companies held to 2033. / A market decline can reduce the facility contribution, but not below the floor. / In 2031 Laura will give co-sponsors a range from the floor to the floor plus half the equity fund's value then. / The other half remains with Laura as a cushion if costs rise or co-sponsors fall short.
A16: BookL | B16: 1 | C16: IBTR | D16: IBTR | E16: Friday order 1 (both books) | F16: future funding | G16: tested | H16: Pick 1 (tested) | I16: Book L: same security, brief and exemplar as Portfolio #1; only the size differs. Book L #1: 1,252 shares, expected Preview total $29,434.48 (ticket), 9.8% of the book (ticket cost / $300,000). | J16: EXAMPLE - team rewrites | K16: At 1 Oct yields, Treasuries for Laura's ten $50,000 payments cost under her $300,000 first deposit; this Dec 2036 Treasury fund is future funding for the fifth. If yields fall over about a quarter of a percentage point by January, her 2028 deposit tops up the earliest; the facility gets less. | L16: =LEN(K16) -> 293 | N16: =LEN(M16) -> 0 | O16: =$B$3-N16 -> 300 | P16: =IF(N16=0,"empty",IF(N16>$B$3,"TOO LONG: cut "&(N16-$B$3)&" characters","OK")) -> empty | Q16: At September 2026 yields the ten payments cost less than $300,000. / The January 2027 deposit buys the liability-hedging portfolio, latest payments first. / A moderate fall in yields would leave some payments for the 2028 deposit to complete
A17: BookL | B17: 2 | C17: IBTQ | D17: IBTQ | E17: Friday order 2 (both books) | F17: future funding | G17: supported | I17: Book L: same security, brief and exemplar as Portfolio #2; only the size differs. Book L #2: 1,311 shares, expected Preview total $31,095.70 (ticket), 10.4% of the book (ticket cost / $300,000). | J17: EXAMPLE - team rewrites | K17: For future funding: the iShares iBonds Dec 2035 Term Treasury ETF is for the fourth of Laura's ten $50,000 residency payments, due 1 Jan 2036. WInS lists no Treasury bond maturing in 2035, so a dated fund of 2035 Treasuries is the closest fit. What it pays out is not fixed. | L17: =LEN(K17) -> 274 | N17: =LEN(M17) -> 0 | O17: =$B$3-N17 -> 300 | P17: =IF(N17=0,"empty",IF(N17>$B$3,"TOO LONG: cut "&(N17-$B$3)&" characters","OK")) -> empty | Q17: Laura's 2027 deposit buys Treasuries maturing before each of her ten $50,000 payments.
A18: BookL | B18: 3 | C18: IBTP | D18: IBTP | E18: Friday order 3 (both books) | F18: future funding | G18: supported | I18: Book L: same security, brief and exemplar as Portfolio #3; only the size differs. Book L #3: 1,362 shares, expected Preview total $32,849.20 (ticket), 10.9% of the book (ticket cost / $300,000). | J18: EXAMPLE - team rewrites | K18: The iShares iBonds Dec 2034 Term Treasury ETF is future funding for Laura's $50,000 residency payment on 1 Jan 2035. At the 1 Oct close its price was almost exactly the value of the 2034 Treasuries it holds; its end value is not fixed. | L18: =LEN(K18) -> 235 | N18: =LEN(M18) -> 0 | O18: =$B$3-N18 -> 300 | P18: =IF(N18=0,"empty",IF(N18>$B$3,"TOO LONG: cut "&(N18-$B$3)&" characters","OK")) -> empty | Q18: Laura's 2027 deposit buys Treasuries maturing before each of her ten $50,000 payments.
A19: BookL | B19: 4 | C19: IBTO | D19: IBTO | E19: Friday order 4 (both books) | F19: future funding | G19: supported | I19: Book L: same security, brief and exemplar as Portfolio #4; only the size differs. Book L #4: 1,503 shares, expected Preview total $34,624.06 (ticket), 11.5% of the book (ticket cost / $300,000). | J19: EXAMPLE - team rewrites | K19: Role: future funding. The iShares iBonds Dec 2033 Term Treasury ETF is for the second of Laura's ten $50,000 payments, on 1 Jan 2034. WInS lists no Treasury bond maturing in 2033, so we use a fund of 2033 Treasuries; the amount it pays out that December is not fixed. | L19: =LEN(K19) -> 267 | N19: =LEN(M19) -> 0 | O19: =$B$3-N19 -> 300 | P19: =IF(N19=0,"empty",IF(N19>$B$3,"TOO LONG: cut "&(N19-$B$3)&" characters","OK")) -> empty | Q19: Laura's 2027 deposit buys Treasuries maturing before each of her ten $50,000 payments.
A20: BookL | B20: 5 | C20: IBTM_L | D20: IBTM | E20: Friday order 5 (Book L only) | F20: future funding | G20: supported | I20: Serves: Laura's 1st payment, $50,000 on 1 Jan 2033 (2027 deposit); Book L holds no floor. Facts: iShares iBonds Dec 2032 Term Treasury ETF (SEEN 29 Sep): ends on or about 15 Dec 2032; monthly income; WInS lists no Treasury maturing in late 2032 (SEEN 29 Sep); Book L = Laura's 2027 deposit dollar for dollar: the floor and the stock fund are bought in 2028 and never appear in WInS. Sizes: Book L #5: 1,678 shares, expected Preview total $36,538.28 (ticket), 12.2% of the book (ticket cost / $300,000); Laura's plan: about $37,000 of her 2027 deposit buys the 2033 payment rung; if its income is reinvested at only 2%, it delivers about $48,000 of the $50,000 (reinvest.rung.IBTM, MODEL; appendix only, never in a note). IPS: "Laura's 2027 deposit buys Treasuries maturing before each of her ten $50,000 payments." One number: none needed [-]. Do not say: the floor (Book L does not hold it); 'repays $50,000'; 'with its income reinvested' as a comfort (whether WInS pays ETF income into cash is UNVERIFIED); nor any word in notes.md s2. Friday: As for the Portfolio book. | J20: EXAMPLE - team rewrites | K20: Role: future funding. The iShares iBonds Dec 2032 Term Treasury ETF ends before the first of Laura's ten $50,000 residency payments, on 1 Jan 2033. WInS lists no Treasury bond maturing in late 2032, so this dated fund is the closest fit; its end value is not fixed. | L20: =LEN(K20) -> 265 | N20: =LEN(M20) -> 0 | O20: =$B$3-N20 -> 300 | P20: =IF(N20=0,"empty",IF(N20>$B$3,"TOO LONG: cut "&(N20-$B$3)&" characters","OK")) -> empty | Q20: Laura's 2027 deposit buys Treasuries maturing before each of her ten $50,000 payments.
A21: BookL | B21: 6 | C21: T41 | D21: T 3.125% 15-Nov-2041 | E21: Friday order 6, first bond (both books) | F21: future funding | G21: supported | H21: Alternate C (supported: why bonds for the last five payments) | I21: Book L: same security, brief and exemplar as Portfolio #6; only the size differs. Book L #6: $29,000 face, expected Preview total $22,501.20 (ticket), 7.5% of the book (ticket cost / $300,000). | J21: EXAMPLE - team rewrites | K21: Role: future funding. The 3.125% Treasury bond maturing 15 Nov 2041 is for the last of Laura's ten $50,000 payments, on 1 Jan 2042. No iBonds Treasury fund ends from 2037 to 2043, so her last five payments use individual bonds; part of each payment comes from reinvested coupons. | L21: =LEN(K21) -> 279 | N21: =LEN(M21) -> 0 | O21: =$B$3-N21 -> 300 | P21: =IF(N21=0,"empty",IF(N21>$B$3,"TOO LONG: cut "&(N21-$B$3)&" characters","OK")) -> empty | Q21: Laura's 2027 deposit buys Treasuries maturing before each of her ten $50,000 payments.
A22: BookL | B22: 7 | C22: T40b | D22: T 4.250% 15-Nov-2040 | E22: Friday order 7 (both books), default: WInS does not list the 1.375% Nov-2040 | F22: future funding | G22: supported | I22: Book L: same security, brief and exemplar as Portfolio #7; only the size differs. Book L #7: $26,000 face, expected Preview total $23,618.74 (ticket), 7.9% of the book (ticket cost / $300,000). | J22: EXAMPLE - team rewrites | K22: Future funding: the 4.250% Treasury bond maturing 15 Nov 2040 is for Laura's ninth $50,000 payment, on 1 Jan 2041. A lower-coupon bond of that date would leave less of her payment resting on reinvested coupons, but WInS does not list one. Its 1 Oct WInS price passed our curve check. | L22: =LEN(K22) -> 283 | N22: =LEN(M22) -> 0 | O22: =$B$3-N22 -> 300 | P22: =IF(N22=0,"empty",IF(N22>$B$3,"TOO LONG: cut "&(N22-$B$3)&" characters","OK")) -> empty | Q22: Laura's 2027 deposit buys Treasuries maturing before each of her ten $50,000 payments.
A23: BookL | B23: 8 | C23: T39 | D23: T 4.375% 15-Nov-2039 | E23: Friday order 8 (both books) | F23: future funding | G23: supported | H23: Alternate B (supported: certainty and the reinvestment discovery); pick 2 if no refined note exists | I23: Book L: same security, brief and exemplar as Portfolio #8; only the size differs. Book L #8: $27,000 face, expected Preview total $25,127.40 (ticket), 8.4% of the book (ticket cost / $300,000). | J23: EXAMPLE - team rewrites | K23: Future funding: the 4.375% Treasury bond maturing 15 Nov 2039 ends about seven weeks before Laura's $50,000 residency payment on 1 Jan 2040. Its price will move, but in her plan, held to maturity, its set coupons and principal cover most of it; the rest depends on reinvested coupons. | L23: =LEN(K23) -> 284 | N23: =LEN(M23) -> 0 | O23: =$B$3-N23 -> 300 | P23: =IF(N23=0,"empty",IF(N23>$B$3,"TOO LONG: cut "&(N23-$B$3)&" characters","OK")) -> empty | Q23: In January 2033 the hedging portfolio becomes the operating reserve, held to maturity and shrinking as each holding pays out.
A24: BookL | B24: 9 | C24: T38 | D24: T 4.500% 15-May-2038 | E24: Friday order 9 (both books) | F24: future funding | G24: supported | I24: Book L: same security, brief and exemplar as Portfolio #9; only the size differs. Book L #9: $29,000 face, expected Preview total $27,847.96 (ticket), 9.2% of the book (ticket cost / $300,000). | J24: EXAMPLE - team rewrites | K24: Role: future funding. The 4.500% Treasury bond maturing 15 May 2038 is the last to mature before Laura's $50,000 residency payment on 1 Jan 2039, so in her plan its money waits about seven and a half months in Treasury bills. Its 1 Oct WInS price passed our curve check. | L24: =LEN(K24) -> 270 | N24: =LEN(M24) -> 0 | O24: =$B$3-N24 -> 300 | P24: =IF(N24=0,"empty",IF(N24>$B$3,"TOO LONG: cut "&(N24-$B$3)&" characters","OK")) -> empty | Q24: Laura's 2027 deposit buys Treasuries maturing before each of her ten $50,000 payments. / At September 2026 yields the ten payments cost less than $300,000.
A25: BookL | B25: 10 | C25: T37 | D25: T 4.750% 15-Feb-2037 | E25: Friday order 10, last bond (both books), if WInS does not list the 5.000% May 2037 | F25: future funding | G25: supported | I25: Book L: same security, brief and exemplar as Portfolio #10; only the size differs. Book L #10: $30,000 face, expected Preview total $29,341.47 (ticket), 9.8% of the book (ticket cost / $300,000). | J25: EXAMPLE - team rewrites | K25: For future funding, the 4.750% Treasury bond maturing 15 Feb 2037 is for Laura's $50,000 payment on 1 Jan 2038. It is the last WInS bond maturing before then, so it ends about ten and a half months early; what the waiting money and its coupons earn can vary. | L25: =LEN(K25) -> 258 | N25: =LEN(M25) -> 0 | O25: =$B$3-N25 -> 300 | P25: =IF(N25=0,"empty",IF(N25>$B$3,"TOO LONG: cut "&(N25-$B$3)&" characters","OK")) -> empty | Q25: Laura's 2027 deposit buys Treasuries maturing before each of her ten $50,000 payments. / In January 2033 the hedging portfolio becomes the operating reserve, held to maturity and shrinking as each holding pays out.
A26: conditional | C26: IBTR_F | D26: IBTR | E26: Friday order 1, only if the refresh says the IBTR test fails | F26: future funding | G26: tested | H26: Pick 1 (tested), if typed | I26: Serves: Laura's 5th payment (1 Jan 2037). The failed-test version of IBTR: the rule decides the trade. Orders 1-10 come from the `--split-from-curve` ticket (more in the dated holdings), and VT on Monday gets the smaller share the refresh prints (friday_checklist.md; `--floor-rule` follows the team's floor definition, s7). The note says 'less is left for the facility', true whichever part shrinks. Tell Ray; WS1 records Friday's figure. IPS: "A moderate fall in yields would leave some payments for the 2028 deposit to complete" / "The January 2027 deposit buys the liability-hedging portfolio, latest payments first." | J26: EXAMPLE - team rewrites | K26: At 1 Oct yields, Treasuries for Laura's ten $50,000 payments cost more than her $300,000 first deposit; this Dec 2036 Treasury fund is future funding for the fifth. As our plan says, her 2028 deposit tops up the earliest ones, so less is left for the facility. | L26: =LEN(K26) -> 260 | N26: =LEN(M26) -> 0 | O26: =$B$3-N26 -> 300 | P26: =IF(N26=0,"empty",IF(N26>$B$3,"TOO LONG: cut "&(N26-$B$3)&" characters","OK")) -> empty | Q26: A moderate fall in yields would leave some payments for the 2028 deposit to complete / The January 2027 deposit buys the liability-hedging portfolio, latest payments first.
A27: conditional | C27: IBTM_R | D27: IBTM | E27: Friday order 5 (Portfolio), only if the 1 Oct vote adopts the backstop sentence | F27: risk management | G27: refined | H27: Pick 2 (refined), if typed and no SW40, SW41 or OD_B | I27: Serves: Laura's 1st payment and the floor. Replaces IBTM_P. Records a change in the policy, decided before the order: the half of the stock fund Laura keeps becomes the first call on a shortfall from coupons or fund end values, before the floor. Type it only if the 1 Oct vote adopts the sentence and the IPS draft carries it the same day (the note says 'our policy'); by 6 Nov the IPS also names the order of use (first a payment shortfall, then facility costs or co-sponsor gaps) and admits the cushion may be partly used (s7). The kept half, about $20,000 in Jan 2028 (half of laura.stock_fund_2028_usd.strips $40,736), is about the size of the 2% gap ($20,399 more today, reinvest.bookL_buffer_cost at_2pct; $33,549 at 0%), so it covers a modest shortfall, not any. If not adopted, type IBTM_P. IPS: "Part of the remainder buys Treasuries maturing in late 2032 that, with coupons reinvested, repay the whole remainder as Laura's facility floor." / "The other half remains with Laura as a cushion if costs rise or co-sponsors fall short." | J27: EXAMPLE - team rewrites | K27: Risk management: the iShares iBonds Dec 2032 Term Treasury ETF holds money for Laura's first $50,000 payment and her facility floor (the least she plans to give). Its end value is not fixed, so our policy makes the stock-fund half she keeps, not the floor, the first call on a shortfall. | L27: =LEN(K27) -> 287 | N27: =LEN(M27) -> 0 | O27: =$B$3-N27 -> 300 | P27: =IF(N27=0,"empty",IF(N27>$B$3,"TOO LONG: cut "&(N27-$B$3)&" characters","OK")) -> empty | Q27: Part of the remainder buys Treasuries maturing in late 2032 that, with coupons reinvested, repay the whole remainder as Laura's facility floor. / The other half remains with Laura as a cushion if costs rise or co-sponsors fall short.
A28: conditional | C28: T40s | D28: T 4.250% 15-Nov-2040 | E28: Friday order 7, if WInS lists the 1.375% Nov-2040 but its price fails the 25bp check | F28: future funding | G28: supported | I28: Serves: Laura's 9th payment (1 Jan 2041). Same bond as T40b. A genuinely new fact decides it: the better bond is listed but its price is stale today. If its price passes on a later check, October trigger D swaps (OD_S, OD_B). IPS: "Laura's 2027 deposit buys Treasuries maturing before each of her ten $50,000 payments." | J28: EXAMPLE - team rewrites | K28: Future funding: the 4.250% Treasury bond maturing 15 Nov 2040 is for the ninth of Laura's ten $50,000 payments. WInS lists a 1.375% bond of that date, which leaves less resting on reinvested coupons, but its 1 Oct price failed our curve check, so we buy this one. | L28: =LEN(K28) -> 263 | N28: =LEN(M28) -> 0 | O28: =$B$3-N28 -> 300 | P28: =IF(N28=0,"empty",IF(N28>$B$3,"TOO LONG: cut "&(N28-$B$3)&" characters","OK")) -> empty | Q28: Laura's 2027 deposit buys Treasuries maturing before each of her ten $50,000 payments.
A29: conditional | C29: SW40 | D29: T 1.375% 15-Nov-2040 | E29: Friday --swap: the 1.375% Nov-2040 is listed and passes (1 Oct rule) | F29: future funding | G29: refined | H29: Pick 2 (refined), if typed | I29: Serves: Laura's 9th payment (1 Jan 2041). Replaces T40b on Friday. CUSIP 912810ST6. Accept a WInS clean price only between 58.474 and 62.116 (25bp band, tickets.md). 'At about the same cost' may be added only after WS1 locks the M9 figures (request 5: $23,266 against $23,146 at forward rates, MODEL). IPS: "Laura's 2027 deposit buys Treasuries maturing before each of her ten $50,000 payments." | J29: EXAMPLE - team rewrites | K29: We chose the 1.375% Treasury bond maturing 15 Nov 2040 over the 4.250% bond of that date for Laura's ninth $50,000 payment (future funding): more of what it pays comes at maturity, so less of her payment rests on reinvesting coupons. Its 1 Oct WInS price passed our curve check. | L29: =LEN(K29) -> 278 | N29: =LEN(M29) -> 0 | O29: =$B$3-N29 -> 300 | P29: =IF(N29=0,"empty",IF(N29>$B$3,"TOO LONG: cut "&(N29-$B$3)&" characters","OK")) -> empty | Q29: Laura's 2027 deposit buys Treasuries maturing before each of her ten $50,000 payments.
A30: conditional | C30: SW41 | D30: T 2.000% 15-Nov-2041 | E30: Friday --swap: the 2.000% Nov-2041 is listed and passes (1 Oct rule) | F30: future funding | G30: refined | H30: Pick 2 (refined), if typed and no SW40 | I30: Serves: Laura's 10th payment (1 Jan 2042). Replaces T41 on Friday. CUSIP 912810TC2. Accept a WInS clean price only between 62.639 and 66.568 (25bp band, tickets.md). IPS: "Laura's 2027 deposit buys Treasuries maturing before each of her ten $50,000 payments." | J30: EXAMPLE - team rewrites | K30: Role: future funding. The 2.000% Treasury bond maturing 15 Nov 2041 is for the last of Laura's ten $50,000 payments. We chose it over the 3.125% bond of the same date: more of what it pays comes at maturity, so less rests on reinvesting coupons. Its 1 Oct price passed our curve check. | L30: =LEN(K30) -> 285 | N30: =LEN(M30) -> 0 | O30: =$B$3-N30 -> 300 | P30: =IF(N30=0,"empty",IF(N30>$B$3,"TOO LONG: cut "&(N30-$B$3)&" characters","OK")) -> empty | Q30: Laura's 2027 deposit buys Treasuries maturing before each of her ten $50,000 payments.
A31: conditional | C31: SW37 | D31: T 5.000% 15-May-2037 | E31: Friday --swap: the 5.000% May-2037 is listed and passes (1 Oct rule) | F31: future funding | G31: supported | I31: Serves: Laura's 6th payment (1 Jan 2038). Replaces T37 on Friday. CUSIP 912810PU6. Accept a WInS clean price only between 95.905 and 99.884 (25bp band, tickets.md). The same rule as T38: the last bond before the payment. IPS: "Laura's 2027 deposit buys Treasuries maturing before each of her ten $50,000 payments." | J31: EXAMPLE - team rewrites | K31: For future funding, the 5.000% Treasury bond maturing 15 May 2037 is for Laura's $50,000 payment on 1 Jan 2038. It is the last Treasury bond maturing before then, so its money waits three months less than with the Feb 2037 bond. Its 1 Oct WInS price passed our curve check. | L31: =LEN(K31) -> 273 | N31: =LEN(M31) -> 0 | O31: =$B$3-N31 -> 300 | P31: =IF(N31=0,"empty",IF(N31>$B$3,"TOO LONG: cut "&(N31-$B$3)&" characters","OK")) -> empty | Q31: Laura's 2027 deposit buys Treasuries maturing before each of her ten $50,000 payments.
A32: conditional | C32: OD_S | D32: T 4.250% 15-Nov-2040 | E32: October trigger D, day 1: sell (october_trade.md) | F32: future funding | G32: refined | I32: Serves: Laura's 9th payment (1 Jan 2041). Sell the whole holding (Portfolio $17,000 face; Book L $26,000). Only after a new fact: the 1.375% was listed on Friday with a stale price (T40s), or was not listed then and is now, and it passes today. Never on the day it was bought. IPS: "Laura's 2027 deposit buys Treasuries maturing before each of her ten $50,000 payments." | J32: EXAMPLE - team rewrites | K32: Role: future funding. We are selling the 4.250% Treasury bond maturing 15 Nov 2040, for Laura's ninth payment, to buy the 1.375% bond of the same date, whose price now passes our curve check. More of what it pays comes at maturity, so less of her payment rests on reinvesting coupons. | L32: =LEN(K32) -> 284 | N32: =LEN(M32) -> 0 | O32: =$B$3-N32 -> 300 | P32: =IF(N32=0,"empty",IF(N32>$B$3,"TOO LONG: cut "&(N32-$B$3)&" characters","OK")) -> empty | Q32: Laura's 2027 deposit buys Treasuries maturing before each of her ten $50,000 payments.
A33: conditional | C33: OD_B | D33: T 1.375% 15-Nov-2040 | E33: October trigger D, day 2: buy (october_trade.md) | F33: future funding | G33: refined | H33: Pick 2 (refined), if trigger D fills | I33: Serves: Laura's 9th payment (1 Jan 2041). Face value from refresh_tickets.py --swap on the day; WInS price inside the 25bp band the refresh prints (28 Sep band: 58.474 to 62.116). Pick 2 if it fills with a saved note by 20 Oct ET. 'At about the same cost' only after WS1 locks request 5. If the bond was not listed on 2 Oct, the last sentence says so instead ('It was not listed on 2 Oct and now passes our curve check'). IPS: "Laura's 2027 deposit buys Treasuries maturing before each of her ten $50,000 payments." | J33: EXAMPLE - team rewrites | K33: Future funding: we are buying the 1.375% Treasury bond maturing 15 Nov 2040 for Laura's ninth payment, in place of the 4.250% bond we sold. More of what it pays comes at maturity, so less rides on reinvested coupons. Its price was stale on 2 Oct and now passes our curve check. | L33: =LEN(K33) -> 277 | N33: =LEN(M33) -> 0 | O33: =$B$3-N33 -> 300 | P33: =IF(N33=0,"empty",IF(N33>$B$3,"TOO LONG: cut "&(N33-$B$3)&" characters","OK")) -> empty | Q33: Laura's 2027 deposit buys Treasuries maturing before each of her ten $50,000 payments.
A34: conditional | C34: OB_S | D34: VT | E34: October trigger B: sell part of VT (rates-fall test) | F34: future funding | G34: tested | H34: Pick 1 (tested), if trigger B fills | I34: Serves: the 2033 payment before growth. Fires only if the refresh on the 14 Oct close says the ten payments cost more than $300,000 on 1 Jan 2027 (today about $292,000, laura.ladder.cost_2027_strips; zero-coupon basis unless WS1 locks a buyable one first). Size from the refresh; only if at least $2,500. In a two-week move the gap stays inside the first payment; if the refresh ever shows more, write 'the earliest payments'. The sale's size follows the team's floor definition (s7; `--floor-rule`): under the IPS's literal wording far less comes out of VT. IPS: "A moderate fall in yields would leave some payments for the 2028 deposit to complete" | J34: EXAMPLE - team rewrites | K34: Yields have fallen, so in our model Laura's ten payments now cost more than her $300,000 first deposit, and her 2028 deposit tops up her first payment, leaving less for the facility. As future funding, we move part of this stock fund into the iShares iBonds Dec 2032 Term Treasury ETF. | L34: =LEN(K34) -> 285 | N34: =LEN(M34) -> 0 | O34: =$B$3-N34 -> 300 | P34: =IF(N34=0,"empty",IF(N34>$B$3,"TOO LONG: cut "&(N34-$B$3)&" characters","OK")) -> empty | Q34: A moderate fall in yields would leave some payments for the 2028 deposit to complete
A35: conditional | C35: OB_B | D35: IBTM | E35: October trigger B: buy IBTM with the VT proceeds | F35: future funding | G35: tested | I35: Serves: Laura's 1st payment and the floor. The buy leg of trigger B; OB_S is the note to feature. IPS: "A moderate fall in yields would leave some payments for the 2028 deposit to complete" / "The January 2027 deposit buys the liability-hedging portfolio, latest payments first." | J35: EXAMPLE - team rewrites | K35: Role: future funding. We are adding to the iShares iBonds Dec 2032 Term Treasury ETF with money from the stock fund. After yields fell, Laura's 2028 deposit must complete her 2033 payment, as our plan allows, so the payments come first. Its end value is not fixed. | L35: =LEN(K35) -> 264 | N35: =LEN(M35) -> 0 | O35: =$B$3-N35 -> 300 | P35: =IF(N35=0,"empty",IF(N35>$B$3,"TOO LONG: cut "&(N35-$B$3)&" characters","OK")) -> empty | Q35: A moderate fall in yields would leave some payments for the 2028 deposit to complete / The January 2027 deposit buys the liability-hedging portfolio, latest payments first.
A36: conditional | C36: OC | D36: VT | E36: October trigger C: spare cash above $6,300 into VT | F36: growth | G36: supported | I36: Serves: growth for the facility contribution. Buy VT with everything above the $3,300 float (october_trade.md). The reason is Laura's plan, not WInS. IPS: "The rest, plus any 2027 remainder, forms the return-seeking portfolio, a global index fund of thousands of companies held to 2033." | J36: EXAMPLE - team rewrites | K36: Role: growth. Our cash is more than fees and rounding need, so the extra goes to the Vanguard Total World Stock ETF: in Laura's plan, money left after her payments and facility floor (the least she plans to give) joins the stock fund held to 2033. | L36: =LEN(K36) -> 247 | N36: =LEN(M36) -> 0 | O36: =$B$3-N36 -> 300 | P36: =IF(N36=0,"empty",IF(N36>$B$3,"TOO LONG: cut "&(N36-$B$3)&" characters","OK")) -> empty | Q36: The rest, plus any 2027 remainder, forms the return-seeking portfolio, a global index fund of thousands of companies held to 2033.
